{
  "slug": "cornus-mas",
  "taxon_key": 3082263,
  "taxon_name": "Cornus mas L.",
  "total_count_in_europe": 130117,
  "points_sampled": 300,
  "points": [
    {
      "lat": 48.5912,
      "lng": 8.7047,
      "country": "DE",
      "year": 2026
    },
    {
      "lat": 55.6409,
      "lng": 13.1951,
      "country": "SE",
      "year": 2026
    },
    {
      "lat": 47.8523,
      "lng": 16.1463,
      "country": "AT",
      "year": 2026
    },
    {
      "lat": 46.8022,
      "lng": 15.8766,
      "country": "AT",
      "year": 2026
    },
    {
      "lat": 49.7451,
      "lng": 6.0936,
      "country": "LU",
      "year": 2026
    },
    {
      "lat": 46.8022,
      "lng": 15.8767,
      "country": "AT",
      "year": 2026
    },
    {
      "lat": 44.6228,
      "lng": 38.0367,
      "country": "RU",
      "year": 2026
    },
    {
      "lat": 44.5885,
      "lng": 37.9736,
      "country": "RU",
      "year": 2026
    },
    {
      "lat": 48.0319,
      "lng": 16.2544,
      "country": "AT",
      "year": 2026
    },
    {
      "lat": 47.0048,
      "lng": 16.0834,
      "country": "AT",
      "year": 2026
    },
    {
      "lat": 44.6901,
      "lng": 37.9003,
      "country": "RU",
      "year": 2026
    },
    {
      "lat": 42.1315,
      "lng": 12.066,
      "country": "IT",
      "year": 2026
    },
    {
      "lat": 48.0308,
      "lng": 16.2546,
      "country": "AT",
      "year": 2026
    },
    {
      "lat": 47.0049,
      "lng": 16.0834,
      "country": "AT",
      "year": 2026
    },
    {
      "lat": 48.8005,
      "lng": 2.204,
      "country": "FR",
      "year": 2026
    },
    {
      "lat": 47.0048,
      "lng": 16.0834,
      "country": "AT",
      "year": 2026
    },
    {
      "lat": 51.65,
      "lng": 4.5,
      "country": "NL",
      "year": 2026
    },
    {
      "lat": 52.45,
      "lng": 6.05,
      "country": "NL",
      "year": 2026
    },
    {
      "lat": 52.1,
      "lng": 4.65,
      "country": "NL",
      "year": 2026
    },
    {
      "lat": 52.3,
      "lng": 4.65,
      "country": "NL",
      "year": 2026
    },
    {
      "lat": 52.0,
      "lng": 5.6,
      "country": "NL",
      "year": 2026
    },
    {
      "lat": 52.3,
      "lng": 4.65,
      "country": "NL",
      "year": 2026
    },
    {
      "lat": 52.1,
      "lng": 5.0,
      "country": "NL",
      "year": 2026
    },
    {
      "lat": 52.35,
      "lng": 4.65,
      "country": "NL",
      "year": 2026
    },
    {
      "lat": 52.1,
      "lng": 5.15,
      "country": "NL",
      "year": 2026
    },
    {
      "lat": 50.75,
      "lng": 5.75,
      "country": "NL",
      "year": 2026
    },
    {
      "lat": 51.5219,
      "lng": 7.3545,
      "country": "DE",
      "year": 2026
    },
    {
      "lat": 50.8858,
      "lng": 6.83,
      "country": "DE",
      "year": 2026
    },
    {
      "lat": 50.3879,
      "lng": 8.0497,
      "country": "DE",
      "year": 2026
    },
    {
      "lat": 53.8121,
      "lng": -1.0823,
      "country": "GB",
      "year": 2026
    },
    {
      "lat": 51.7156,
      "lng": -2.194,
      "country": "GB",
      "year": 2026
    },
    {
      "lat": 48.8513,
      "lng": 2.2456,
      "country": "FR",
      "year": 2026
    },
    {
      "lat": 48.0344,
      "lng": 16.2556,
      "country": "AT",
      "year": 2026
    },
    {
      "lat": 44.0194,
      "lng": 39.3605,
      "country": "RU",
      "year": 2026
    },
    {
      "lat": 53.1127,
      "lng": -2.2721,
      "country": "GB",
      "year": 2026
    },
    {
      "lat": 48.0364,
      "lng": -1.7231,
      "country": "FR",
      "year": 2026
    },
    {
      "lat": 47.9982,
      "lng": 16.264,
      "country": "AT",
      "year": 2026
    },
    {
      "lat": 51.9,
      "lng": 4.25,
      "country": "NL",
      "year": 2026
    },
    {
      "lat": 52.25,
      "lng": 6.15,
      "country": "NL",
      "year": 2026
    },
    {
      "lat": 50.75,
      "lng": 5.75,
      "country": "NL",
      "year": 2026
    },
    {
      "lat": 52.35,
      "lng": 4.8,
      "country": "NL",
      "year": 2026
    },
    {
      "lat": 52.0,
      "lng": 5.6,
      "country": "NL",
      "year": 2026
    },
    {
      "lat": 51.85,
      "lng": 4.55,
      "country": "NL",
      "year": 2026
    },
    {
      "lat": 51.95,
      "lng": 4.2,
      "country": "NL",
      "year": 2026
    },
    {
      "lat": 51.65,
      "lng": 4.15,
      "country": "NL",
      "year": 2026
    },
    {
      "lat": 52.3,
      "lng": 4.9,
      "country": "NL",
      "year": 2026
    },
    {
      "lat": 52.05,
      "lng": 5.1,
      "country": "NL",
      "year": 2026
    },
    {
      "lat": 51.9,
      "lng": 6.7,
      "country": "NL",
      "year": 2026
    },
    {
      "lat": 51.2,
      "lng": 3.85,
      "country": "NL",
      "year": 2026
    },
    {
      "lat": 52.3,
      "lng": 4.65,
      "country": "NL",
      "year": 2026
    },
    {
      "lat": 52.1,
      "lng": 5.1,
      "country": "NL",
      "year": 2026
    },
    {
      "lat": 52.05,
      "lng": 4.35,
      "country": "NL",
      "year": 2026
    },
    {
      "lat": 52.45,
      "lng": 6.05,
      "country": "NL",
      "year": 2026
    },
    {
      "lat": 52.05,
      "lng": 4.45,
      "country": "NL",
      "year": 2026
    },
    {
      "lat": 50.8,
      "lng": 5.65,
      "country": "NL",
      "year": 2026
    },
    {
      "lat": 50.75,
      "lng": 5.75,
      "country": "NL",
      "year": 2026
    },
    {
      "lat": 52.6,
      "lng": 4.65,
      "country": "NL",
      "year": 2026
    },
    {
      "lat": 52.0,
      "lng": 4.3,
      "country": "NL",
      "year": 2026
    },
    {
      "lat": 52.15,
      "lng": 4.45,
      "country": "NL",
      "year": 2026
    },
    {
      "lat": 52.05,
      "lng": 4.55,
      "country": "NL",
      "year": 2026
    },
    {
      "lat": 51.85,
      "lng": 4.35,
      "country": "NL",
      "year": 2026
    },
    {
      "lat": 52.15,
      "lng": 4.45,
      "country": "NL",
      "year": 2026
    },
    {
      "lat": 52.0,
      "lng": 4.25,
      "country": "NL",
      "year": 2026
    },
    {
      "lat": 52.15,
      "lng": 4.45,
      "country": "NL",
      "year": 2026
    },
    {
      "lat": 51.95,
      "lng": 6.55,
      "country": "NL",
      "year": 2026
    },
    {
      "lat": 52.0,
      "lng": 4.3,
      "country": "NL",
      "year": 2026
    },
    {
      "lat": 51.5,
      "lng": 4.45,
      "country": "NL",
      "year": 2026
    },
    {
      "lat": 50.75,
      "lng": 5.65,
      "country": "NL",
      "year": 2026
    },
    {
      "lat": 52.0,
      "lng": 4.4,
      "country": "NL",
      "year": 2026
    },
    {
      "lat": 52.15,
      "lng": 4.45,
      "country": "NL",
      "year": 2026
    },
    {
      "lat": 52.0,
      "lng": 4.4,
      "country": "NL",
      "year": 2026
    },
    {
      "lat": 52.05,
      "lng": 4.55,
      "country": "NL",
      "year": 2026
    },
    {
      "lat": 51.8,
      "lng": 4.95,
      "country": "NL",
      "year": 2026
    },
    {
      "lat": 51.85,
      "lng": 5.35,
      "country": "NL",
      "year": 2026
    },
    {
      "lat": 50.8,
      "lng": 5.65,
      "country": "NL",
      "year": 2026
    },
    {
      "lat": 50.85,
      "lng": 5.9,
      "country": "NL",
      "year": 2026
    },
    {
      "lat": 51.95,
      "lng": 4.45,
      "country": "NL",
      "year": 2026
    },
    {
      "lat": 52.1,
      "lng": 4.5,
      "country": "NL",
      "year": 2026
    },
    {
      "lat": 52.4,
      "lng": 6.25,
      "country": "NL",
      "year": 2026
    },
    {
      "lat": 51.2763,
      "lng": 6.407,
      "country": "DE",
      "year": 2026
    },
    {
      "lat": 49.1502,
      "lng": 9.2853,
      "country": "DE",
      "year": 2026
    },
    {
      "lat": 49.1259,
      "lng": 2.3446,
      "country": "FR",
      "year": 2026
    },
    {
      "lat": 51.4754,
      "lng": -0.0233,
      "country": "GB",
      "year": 2026
    },
    {
      "lat": 45.7757,
      "lng": 15.9315,
      "country": "HR",
      "year": 2026
    },
    {
      "lat": 48.0128,
      "lng": 16.2298,
      "country": "AT",
      "year": 2026
    },
    {
      "lat": 48.9025,
      "lng": 8.466,
      "country": "DE",
      "year": 2026
    },
    {
      "lat": 45.4099,
      "lng": 11.5257,
      "country": "IT",
      "year": 2026
    },
    {
      "lat": 41.2685,
      "lng": 23.1623,
      "country": "GR",
      "year": 2026
    },
    {
      "lat": 50.3663,
      "lng": 2.9648,
      "country": "FR",
      "year": 2026
    },
    {
      "lat": 41.5107,
      "lng": 35.5712,
      "country": "TR",
      "year": 2026
    },
    {
      "lat": 51.2369,
      "lng": -1.1496,
      "country": "GB",
      "year": 2026
    },
    {
      "lat": 50.8564,
      "lng": 6.1569,
      "country": "DE",
      "year": 2026
    },
    {
      "lat": 50.8855,
      "lng": 6.8653,
      "country": "DE",
      "year": 2026
    },
    {
      "lat": 49.4694,
      "lng": 8.4846,
      "country": "DE",
      "year": 2026
    },
    {
      "lat": 51.2817,
      "lng": 6.3775,
      "country": "DE",
      "year": 2026
    },
    {
      "lat": 45.4861,
      "lng": 8.036,
      "country": "IT",
      "year": 2026
    },
    {
      "lat": 48.1279,
      "lng": 16.2473,
      "country": "AT",
      "year": 2026
    },
    {
      "lat": 52.3548,
      "lng": 9.7391,
      "country": "DE",
      "year": 2026
    },
    {
      "lat": 44.5634,
      "lng": 16.0882,
      "country": "BA",
      "year": 2026
    },
    {
      "lat": 44.3324,
      "lng": 38.8015,
      "country": "RU",
      "year": 2026
    },
    {
      "lat": 41.8384,
      "lng": 46.2402,
      "country": "GE",
      "year": 2026
    },
    {
      "lat": 45.347,
      "lng": 11.9592,
      "country": "IT",
      "year": 2026
    },
    {
      "lat": 48.1524,
      "lng": 16.9555,
      "country": "AT",
      "year": 2026
    },
    {
      "lat": 45.6297,
      "lng": 9.8973,
      "country": "IT",
      "year": 2026
    },
    {
      "lat": 47.9898,
      "lng": 7.8946,
      "country": "DE",
      "year": 2026
    },
    {
      "lat": 50.7914,
      "lng": 4.4117,
      "country": "BE",
      "year": 2026
    },
    {
      "lat": 49.8875,
      "lng": 2.5114,
      "country": "FR",
      "year": 2026
    },
    {
      "lat": 48.5238,
      "lng": 7.804,
      "country": "FR",
      "year": 2026
    },
    {
      "lat": 45.5911,
      "lng": 9.7431,
      "country": "IT",
      "year": 2026
    },
    {
      "lat": 43.6311,
      "lng": 39.7129,
      "country": "RU",
      "year": 2026
    },
    {
      "lat": 45.2808,
      "lng": 9.7619,
      "country": "IT",
      "year": 2026
    },
    {
      "lat": 48.2262,
      "lng": 16.4598,
      "country": "AT",
      "year": 2026
    },
    {
      "lat": 41.9884,
      "lng": 14.5251,
      "country": "IT",
      "year": 2026
    },
    {
      "lat": 43.8959,
      "lng": 3.9351,
      "country": "FR",
      "year": 2026
    },
    {
      "lat": 49.5333,
      "lng": 4.7222,
      "country": "FR",
      "year": 2026
    },
    {
      "lat": 44.8095,
      "lng": 4.9273,
      "country": "FR",
      "year": 2026
    },
    {
      "lat": 42.2918,
      "lng": 42.7652,
      "country": "GE",
      "year": 2026
    },
    {
      "lat": 48.8685,
      "lng": 5.0188,
      "country": "FR",
      "year": 2026
    },
    {
      "lat": 51.4376,
      "lng": -0.8801,
      "country": "GB",
      "year": 2026
    },
    {
      "lat": 45.6643,
      "lng": 11.2568,
      "country": "IT",
      "year": 2026
    },
    {
      "lat": 49.7257,
      "lng": 6.683,
      "country": "DE",
      "year": 2026
    },
    {
      "lat": 45.7686,
      "lng": 13.8877,
      "country": "SI",
      "year": 2026
    },
    {
      "lat": 45.7834,
      "lng": 11.7123,
      "country": "IT",
      "year": 2026
    },
    {
      "lat": 45.2199,
      "lng": 8.2296,
      "country": "IT",
      "year": 2026
    },
    {
      "lat": 48.152,
      "lng": 16.9538,
      "country": "AT",
      "year": 2026
    },
    {
      "lat": 45.5441,
      "lng": 9.2079,
      "country": "IT",
      "year": 2026
    },
    {
      "lat": 44.3307,
      "lng": 38.8025,
      "country": "RU",
      "year": 2026
    },
    {
      "lat": 50.6008,
      "lng": 3.0203,
      "country": "FR",
      "year": 2026
    },
    {
      "lat": 51.4539,
      "lng": -2.6075,
      "country": "GB",
      "year": 2026
    },
    {
      "lat": 49.7178,
      "lng": 6.4533,
      "country": "LU",
      "year": 2026
    },
    {
      "lat": 48.5872,
      "lng": 7.7023,
      "country": "FR",
      "year": 2026
    },
    {
      "lat": 48.54,
      "lng": -1.7592,
      "country": "FR",
      "year": 2026
    },
    {
      "lat": 45.489,
      "lng": 7.9108,
      "country": "IT",
      "year": 2026
    },
    {
      "lat": 44.2062,
      "lng": 4.126,
      "country": "FR",
      "year": 2026
    },
    {
      "lat": 44.6817,
      "lng": 37.7871,
      "country": "RU",
      "year": 2026
    },
    {
      "lat": 49.5333,
      "lng": 4.7222,
      "country": "FR",
      "year": 2026
    },
    {
      "lat": 44.3351,
      "lng": 38.806,
      "country": "RU",
      "year": 2026
    },
    {
      "lat": 55.8726,
      "lng": 12.8311,
      "country": "SE",
      "year": 2026
    },
    {
      "lat": 51.95,
      "lng": 5.95,
      "country": "NL",
      "year": 2026
    },
    {
      "lat": 52.05,
      "lng": 5.1,
      "country": "NL",
      "year": 2026
    },
    {
      "lat": 52.15,
      "lng": 4.6,
      "country": "NL",
      "year": 2026
    },
    {
      "lat": 52.25,
      "lng": 7.0,
      "country": "NL",
      "year": 2026
    },
    {
      "lat": 52.25,
      "lng": 5.5,
      "country": "NL",
      "year": 2026
    },
    {
      "lat": 50.75,
      "lng": 5.9,
      "country": "NL",
      "year": 2026
    },
    {
      "lat": 51.9,
      "lng": 4.3,
      "country": "NL",
      "year": 2026
    },
    {
      "lat": 50.95,
      "lng": 5.85,
      "country": "NL",
      "year": 2026
    },
    {
      "lat": 52.35,
      "lng": 4.8,
      "country": "NL",
      "year": 2026
    },
    {
      "lat": 52.15,
      "lng": 6.35,
      "country": "NL",
      "year": 2026
    },
    {
      "lat": 50.8,
      "lng": 5.65,
      "country": "NL",
      "year": 2026
    },
    {
      "lat": 51.55,
      "lng": 5.1,
      "country": "NL",
      "year": 2026
    },
    {
      "lat": 52.1,
      "lng": 4.3,
      "country": "NL",
      "year": 2026
    },
    {
      "lat": 51.65,
      "lng": 5.35,
      "country": "NL",
      "year": 2026
    },
    {
      "lat": 52.0,
      "lng": 4.65,
      "country": "NL",
      "year": 2026
    },
    {
      "lat": 52.45,
      "lng": 5.5,
      "country": "NL",
      "year": 2026
    },
    {
      "lat": 52.05,
      "lng": 4.3,
      "country": "NL",
      "year": 2026
    },
    {
      "lat": 52.85,
      "lng": 4.8,
      "country": "NL",
      "year": 2026
    },
    {
      "lat": 50.75,
      "lng": 5.65,
      "country": "NL",
      "year": 2026
    },
    {
      "lat": 51.9,
      "lng": 4.45,
      "country": "NL",
      "year": 2026
    },
    {
      "lat": 52.05,
      "lng": 4.45,
      "country": "NL",
      "year": 2026
    },
    {
      "lat": 51.85,
      "lng": 6.35,
      "country": "NL",
      "year": 2026
    },
    {
      "lat": 52.0,
      "lng": 5.95,
      "country": "NL",
      "year": 2026
    },
    {
      "lat": 51.25,
      "lng": 4.05,
      "country": "NL",
      "year": 2026
    },
    {
      "lat": 52.15,
      "lng": 5.3,
      "country": "NL",
      "year": 2026
    },
    {
      "lat": 51.95,
      "lng": 5.65,
      "country": "NL",
      "year": 2026
    },
    {
      "lat": 50.75,
      "lng": 5.9,
      "country": "NL",
      "year": 2026
    },
    {
      "lat": 51.1433,
      "lng": 6.8624,
      "country": "DE",
      "year": 2026
    },
    {
      "lat": 51.95,
      "lng": 4.6,
      "country": "NL",
      "year": 2026
    },
    {
      "lat": 51.15,
      "lng": 6.0,
      "country": "NL",
      "year": 2026
    },
    {
      "lat": 50.75,
      "lng": 5.65,
      "country": "NL",
      "year": 2026
    },
    {
      "lat": 51.9,
      "lng": 6.45,
      "country": "NL",
      "year": 2026
    },
    {
      "lat": 51.236,
      "lng": 6.8368,
      "country": "DE",
      "year": 2026
    },
    {
      "lat": 51.8,
      "lng": 6.0,
      "country": "NL",
      "year": 2026
    },
    {
      "lat": 51.9,
      "lng": 4.3,
      "country": "NL",
      "year": 2026
    },
    {
      "lat": 52.1,
      "lng": 6.25,
      "country": "NL",
      "year": 2026
    },
    {
      "lat": 49.7178,
      "lng": 6.4533,
      "country": "LU",
      "year": 2026
    },
    {
      "lat": 51.55,
      "lng": 5.1,
      "country": "NL",
      "year": 2026
    },
    {
      "lat": 52.1,
      "lng": 5.0,
      "country": "NL",
      "year": 2026
    },
    {
      "lat": 52.1,
      "lng": 5.05,
      "country": "NL",
      "year": 2026
    },
    {
      "lat": 52.45,
      "lng": 5.5,
      "country": "NL",
      "year": 2026
    },
    {
      "lat": 51.9,
      "lng": 5.4,
      "country": "NL",
      "year": 2026
    },
    {
      "lat": 52.1,
      "lng": 5.0,
      "country": "NL",
      "year": 2026
    },
    {
      "lat": 52.1,
      "lng": 4.4,
      "country": "NL",
      "year": 2026
    },
    {
      "lat": 52.95,
      "lng": 6.95,
      "country": "NL",
      "year": 2026
    },
    {
      "lat": 52.4,
      "lng": 5.55,
      "country": "NL",
      "year": 2026
    },
    {
      "lat": 50.9,
      "lng": 5.95,
      "country": "NL",
      "year": 2026
    },
    {
      "lat": 50.9207,
      "lng": 6.9503,
      "country": "DE",
      "year": 2026
    },
    {
      "lat": 51.75,
      "lng": 5.75,
      "country": "NL",
      "year": 2026
    },
    {
      "lat": 50.75,
      "lng": 5.75,
      "country": "NL",
      "year": 2026
    },
    {
      "lat": 52.0,
      "lng": 5.95,
      "country": "NL",
      "year": 2026
    },
    {
      "lat": 51.1,
      "lng": 6.0,
      "country": "NL",
      "year": 2026
    },
    {
      "lat": 52.35,
      "lng": 4.95,
      "country": "NL",
      "year": 2026
    },
    {
      "lat": 52.15,
      "lng": 6.45,
      "country": "NL",
      "year": 2026
    },
    {
      "lat": 51.95,
      "lng": 5.55,
      "country": "NL",
      "year": 2026
    },
    {
      "lat": 53.1,
      "lng": 6.0,
      "country": "NL",
      "year": 2026
    },
    {
      "lat": 51.85,
      "lng": 4.65,
      "country": "NL",
      "year": 2026
    },
    {
      "lat": 52.1,
      "lng": 4.45,
      "country": "NL",
      "year": 2026
    },
    {
      "lat": 52.0,
      "lng": 6.5,
      "country": "NL",
      "year": 2026
    },
    {
      "lat": 52.0,
      "lng": 5.95,
      "country": "NL",
      "year": 2026
    },
    {
      "lat": 52.05,
      "lng": 4.65,
      "country": "NL",
      "year": 2026
    },
    {
      "lat": 51.1,
      "lng": 6.0,
      "country": "NL",
      "year": 2026
    },
    {
      "lat": 52.1,
      "lng": 4.65,
      "country": "NL",
      "year": 2026
    },
    {
      "lat": 52.05,
      "lng": 4.55,
      "country": "NL",
      "year": 2026
    },
    {
      "lat": 51.95,
      "lng": 5.95,
      "country": "NL",
      "year": 2026
    },
    {
      "lat": 48.629,
      "lng": 6.0313,
      "country": "FR",
      "year": 2026
    },
    {
      "lat": 51.6,
      "lng": 5.5,
      "country": "NL",
      "year": 2026
    },
    {
      "lat": 52.35,
      "lng": 4.95,
      "country": "NL",
      "year": 2026
    },
    {
      "lat": 50.85,
      "lng": 5.9,
      "country": "NL",
      "year": 2026
    },
    {
      "lat": 51.65,
      "lng": 5.35,
      "country": "NL",
      "year": 2026
    },
    {
      "lat": 50.85,
      "lng": 5.9,
      "country": "NL",
      "year": 2026
    },
    {
      "lat": 50.8,
      "lng": 5.65,
      "country": "NL",
      "year": 2026
    },
    {
      "lat": 50.8,
      "lng": 5.65,
      "country": "NL",
      "year": 2026
    },
    {
      "lat": 52.05,
      "lng": 5.0,
      "country": "NL",
      "year": 2026
    },
    {
      "lat": 52.1,
      "lng": 4.95,
      "country": "NL",
      "year": 2026
    },
    {
      "lat": 51.5,
      "lng": 5.95,
      "country": "NL",
      "year": 2026
    },
    {
      "lat": 52.25,
      "lng": 6.15,
      "country": "NL",
      "year": 2026
    },
    {
      "lat": 52.05,
      "lng": 5.0,
      "country": "NL",
      "year": 2026
    },
    {
      "lat": 52.4,
      "lng": 5.3,
      "country": "NL",
      "year": 2026
    },
    {
      "lat": 51.8,
      "lng": 4.35,
      "country": "NL",
      "year": 2026
    },
    {
      "lat": 52.8,
      "lng": 7.0,
      "country": "NL",
      "year": 2026
    },
    {
      "lat": 50.8,
      "lng": 5.65,
      "country": "NL",
      "year": 2026
    },
    {
      "lat": 52.6,
      "lng": 4.65,
      "country": "NL",
      "year": 2026
    },
    {
      "lat": 51.85,
      "lng": 4.55,
      "country": "NL",
      "year": 2026
    },
    {
      "lat": 50.8,
      "lng": 5.65,
      "country": "NL",
      "year": 2026
    },
    {
      "lat": 51.95,
      "lng": 6.3,
      "country": "NL",
      "year": 2026
    },
    {
      "lat": 51.65,
      "lng": 4.75,
      "country": "NL",
      "year": 2026
    },
    {
      "lat": 52.3,
      "lng": 4.6,
      "country": "NL",
      "year": 2026
    },
    {
      "lat": 51.6,
      "lng": 4.3,
      "country": "NL",
      "year": 2026
    },
    {
      "lat": 52.15,
      "lng": 4.45,
      "country": "NL",
      "year": 2026
    },
    {
      "lat": 51.75,
      "lng": 4.65,
      "country": "NL",
      "year": 2026
    },
    {
      "lat": 51.35,
      "lng": 5.5,
      "country": "NL",
      "year": 2026
    },
    {
      "lat": 50.8,
      "lng": 5.65,
      "country": "NL",
      "year": 2026
    },
    {
      "lat": 52.05,
      "lng": 4.85,
      "country": "NL",
      "year": 2026
    },
    {
      "lat": 52.0,
      "lng": 5.15,
      "country": "NL",
      "year": 2026
    },
    {
      "lat": 51.85,
      "lng": 4.6,
      "country": "NL",
      "year": 2026
    },
    {
      "lat": 52.3,
      "lng": 4.8,
      "country": "NL",
      "year": 2026
    },
    {
      "lat": 52.1,
      "lng": 4.6,
      "country": "NL",
      "year": 2026
    },
    {
      "lat": 50.8,
      "lng": 5.9,
      "country": "NL",
      "year": 2026
    },
    {
      "lat": 52.6,
      "lng": 5.05,
      "country": "NL",
      "year": 2026
    },
    {
      "lat": 51.8,
      "lng": 5.3,
      "country": "NL",
      "year": 2026
    },
    {
      "lat": 52.3,
      "lng": 4.8,
      "country": "NL",
      "year": 2026
    },
    {
      "lat": 49.6872,
      "lng": 6.4146,
      "country": "LU",
      "year": 2026
    },
    {
      "lat": 50.8,
      "lng": 5.65,
      "country": "NL",
      "year": 2026
    },
    {
      "lat": 50.8,
      "lng": 5.9,
      "country": "NL",
      "year": 2026
    },
    {
      "lat": 52.15,
      "lng": 4.5,
      "country": "NL",
      "year": 2026
    },
    {
      "lat": 52.45,
      "lng": 5.65,
      "country": "NL",
      "year": 2026
    },
    {
      "lat": 51.75,
      "lng": 5.7,
      "country": "NL",
      "year": 2026
    },
    {
      "lat": 50.85,
      "lng": 6.05,
      "country": "NL",
      "year": 2026
    },
    {
      "lat": 51.8,
      "lng": 4.75,
      "country": "NL",
      "year": 2026
    },
    {
      "lat": 52.25,
      "lng": 6.2,
      "country": "NL",
      "year": 2026
    },
    {
      "lat": 52.05,
      "lng": 4.5,
      "country": "NL",
      "year": 2026
    },
    {
      "lat": 52.0,
      "lng": 4.35,
      "country": "NL",
      "year": 2026
    },
    {
      "lat": 50.95,
      "lng": 5.85,
      "country": "NL",
      "year": 2026
    },
    {
      "lat": 52.1,
      "lng": 4.65,
      "country": "NL",
      "year": 2026
    },
    {
      "lat": 52.45,
      "lng": 4.95,
      "country": "NL",
      "year": 2026
    },
    {
      "lat": 50.0775,
      "lng": 8.5362,
      "country": "DE",
      "year": 2026
    },
    {
      "lat": 52.05,
      "lng": 6.5,
      "country": "NL",
      "year": 2026
    },
    {
      "lat": 52.45,
      "lng": 5.7,
      "country": "NL",
      "year": 2026
    },
    {
      "lat": 51.55,
      "lng": 4.6,
      "country": "NL",
      "year": 2026
    },
    {
      "lat": 51.45,
      "lng": 4.45,
      "country": "NL",
      "year": 2026
    },
    {
      "lat": 52.25,
      "lng": 6.15,
      "country": "NL",
      "year": 2026
    },
    {
      "lat": 52.1,
      "lng": 4.65,
      "country": "NL",
      "year": 2026
    },
    {
      "lat": 51.85,
      "lng": 6.35,
      "country": "NL",
      "year": 2026
    },
    {
      "lat": 52.15,
      "lng": 4.5,
      "country": "NL",
      "year": 2026
    },
    {
      "lat": 51.9,
      "lng": 6.55,
      "country": "NL",
      "year": 2026
    },
    {
      "lat": 51.85,
      "lng": 6.35,
      "country": "NL",
      "year": 2026
    },
    {
      "lat": 53.2,
      "lng": 6.55,
      "country": "NL",
      "year": 2026
    },
    {
      "lat": 50.75,
      "lng": 5.9,
      "country": "NL",
      "year": 2026
    },
    {
      "lat": 52.0,
      "lng": 4.15,
      "country": "NL",
      "year": 2026
    },
    {
      "lat": 52.05,
      "lng": 4.85,
      "country": "NL",
      "year": 2026
    },
    {
      "lat": 51.95,
      "lng": 5.6,
      "country": "NL",
      "year": 2026
    },
    {
      "lat": 52.05,
      "lng": 4.45,
      "country": "NL",
      "year": 2026
    },
    {
      "lat": 50.8,
      "lng": 5.65,
      "country": "NL",
      "year": 2026
    },
    {
      "lat": 51.9,
      "lng": 4.45,
      "country": "NL",
      "year": 2026
    },
    {
      "lat": 52.3,
      "lng": 5.45,
      "country": "NL",
      "year": 2026
    },
    {
      "lat": 51.8,
      "lng": 4.25,
      "country": "NL",
      "year": 2026
    },
    {
      "lat": 52.45,
      "lng": 6.05,
      "country": "NL",
      "year": 2026
    },
    {
      "lat": 51.95,
      "lng": 4.5,
      "country": "NL",
      "year": 2026
    },
    {
      "lat": 52.1,
      "lng": 4.5,
      "country": "NL",
      "year": 2026
    },
    {
      "lat": 51.45,
      "lng": 4.25,
      "country": "NL",
      "year": 2026
    },
    {
      "lat": 51.85,
      "lng": 4.3,
      "country": "NL",
      "year": 2026
    },
    {
      "lat": 52.65,
      "lng": 5.05,
      "country": "NL",
      "year": 2026
    },
    {
      "lat": 51.25,
      "lng": 4.05,
      "country": "NL",
      "year": 2026
    },
    {
      "lat": 51.95,
      "lng": 5.7,
      "country": "NL",
      "year": 2026
    },
    {
      "lat": 50.9,
      "lng": 6.05,
      "country": "NL",
      "year": 2026
    },
    {
      "lat": 53.2,
      "lng": 5.95,
      "country": "NL",
      "year": 2026
    },
    {
      "lat": 52.25,
      "lng": 5.5,
      "country": "NL",
      "year": 2026
    },
    {
      "lat": 52.05,
      "lng": 5.15,
      "country": "NL",
      "year": 2026
    },
    {
      "lat": 52.15,
      "lng": 4.5,
      "country": "NL",
      "year": 2026
    },
    {
      "lat": 52.3,
      "lng": 6.85,
      "country": "NL",
      "year": 2026
    },
    {
      "lat": 52.35,
      "lng": 5.9,
      "country": "NL",
      "year": 2026
    },
    {
      "lat": 52.35,
      "lng": 4.85,
      "country": "NL",
      "year": 2026
    },
    {
      "lat": 50.8,
      "lng": 5.8,
      "country": "NL",
      "year": 2026
    },
    {
      "lat": 51.9,
      "lng": 5.85,
      "country": "NL",
      "year": 2026
    },
    {
      "lat": 52.15,
      "lng": 4.45,
      "country": "NL",
      "year": 2026
    },
    {
      "lat": 50.85,
      "lng": 5.75,
      "country": "NL",
      "year": 2026
    },
    {
      "lat": 51.3,
      "lng": 5.5,
      "country": "NL",
      "year": 2026
    },
    {
      "lat": 50.95,
      "lng": 5.85,
      "country": "NL",
      "year": 2026
    },
    {
      "lat": 45.7179,
      "lng": 9.6952,
      "country": "IT",
      "year": 2026
    },
    {
      "lat": 45.1001,
      "lng": 8.2834,
      "country": "IT",
      "year": 2026
    },
    {
      "lat": 52.2758,
      "lng": 10.5799,
      "country": "DE",
      "year": 2026
    }
  ],
  "source": "GBIF.org occurrence search API",
  "source_url": "https://www.gbif.org/species/3082263",
  "accessed": "2026-05-17",
  "bulgaria_points": [
    {
      "lat": 41.3838,
      "lng": 23.2016,
      "year": 2026
    },
    {
      "lat": 42.6626,
      "lng": 23.2986,
      "year": 2026
    },
    {
      "lat": 42.6949,
      "lng": 23.325,
      "year": 2026
    },
    {
      "lat": 43.0532,
      "lng": 23.4091,
      "year": 2026
    },
    {
      "lat": 42.4136,
      "lng": 23.0264,
      "year": 2026
    },
    {
      "lat": 42.7152,
      "lng": 27.7299,
      "year": 2026
    },
    {
      "lat": 42.6993,
      "lng": 23.3719,
      "year": 2026
    },
    {
      "lat": 43.0422,
      "lng": 27.7097,
      "year": 2026
    },
    {
      "lat": 41.8825,
      "lng": 25.328,
      "year": 2026
    },
    {
      "lat": 41.9377,
      "lng": 25.3603,
      "year": 2026
    },
    {
      "lat": 41.9091,
      "lng": 25.3135,
      "year": 2026
    },
    {
      "lat": 42.7169,
      "lng": 27.7369,
      "year": 2026
    },
    {
      "lat": 43.0677,
      "lng": 25.6318,
      "year": 2026
    },
    {
      "lat": 42.6306,
      "lng": 27.5744,
      "year": 2026
    },
    {
      "lat": 42.9916,
      "lng": 27.8868,
      "year": 2026
    },
    {
      "lat": 41.9778,
      "lng": 24.8655,
      "year": 2026
    },
    {
      "lat": 42.6931,
      "lng": 24.4496,
      "year": 2026
    },
    {
      "lat": 41.6913,
      "lng": 24.3272,
      "year": 2026
    },
    {
      "lat": 43.1995,
      "lng": 23.4998,
      "year": 2026
    },
    {
      "lat": 42.734,
      "lng": 26.3047,
      "year": 2025
    },
    {
      "lat": 42.7085,
      "lng": 26.3273,
      "year": 2025
    },
    {
      "lat": 43.0993,
      "lng": 23.4859,
      "year": 2025
    },
    {
      "lat": 43.0888,
      "lng": 23.37,
      "year": 2025
    },
    {
      "lat": 43.3432,
      "lng": 28.0543,
      "year": 2025
    },
    {
      "lat": 43.293,
      "lng": 26.9002,
      "year": 2025
    },
    {
      "lat": 43.3258,
      "lng": 26.7544,
      "year": 2025
    },
    {
      "lat": 41.9895,
      "lng": 26.4875,
      "year": 2025
    },
    {
      "lat": 41.6885,
      "lng": 23.7202,
      "year": 2025
    },
    {
      "lat": 43.0247,
      "lng": 23.2436,
      "year": 2025
    },
    {
      "lat": 41.7171,
      "lng": 25.4663,
      "year": 2025
    },
    {
      "lat": 43.3326,
      "lng": 28.0605,
      "year": 2025
    },
    {
      "lat": 42.5656,
      "lng": 23.0494,
      "year": 2024
    },
    {
      "lat": 43.2565,
      "lng": 26.9211,
      "year": 2024
    },
    {
      "lat": 42.7332,
      "lng": 27.7072,
      "year": 2024
    },
    {
      "lat": 42.0672,
      "lng": 26.3547,
      "year": 2024
    },
    {
      "lat": 41.6332,
      "lng": 24.3424,
      "year": 2024
    },
    {
      "lat": 43.2769,
      "lng": 27.1172,
      "year": 2024
    },
    {
      "lat": 43.0472,
      "lng": 24.186,
      "year": 2024
    },
    {
      "lat": 42.2962,
      "lng": 27.7361,
      "year": 2023
    },
    {
      "lat": 41.8197,
      "lng": 23.4875,
      "year": 2023
    },
    {
      "lat": 43.0696,
      "lng": 23.46,
      "year": 2023
    },
    {
      "lat": 43.0307,
      "lng": 25.3149,
      "year": 2023
    },
    {
      "lat": 43.164,
      "lng": 24.1703,
      "year": 2023
    },
    {
      "lat": 41.9827,
      "lng": 27.5124,
      "year": 2023
    },
    {
      "lat": 43.4024,
      "lng": 25.563,
      "year": 2023
    },
    {
      "lat": 42.8499,
      "lng": 26.7574,
      "year": 2023
    },
    {
      "lat": 42.5953,
      "lng": 23.4334,
      "year": 2023
    },
    {
      "lat": 42.1498,
      "lng": 23.3701,
      "year": 2023
    },
    {
      "lat": 43.1531,
      "lng": 26.7772,
      "year": 2023
    },
    {
      "lat": 43.1039,
      "lng": 23.4817,
      "year": 2022
    },
    {
      "lat": 41.6213,
      "lng": 25.2508,
      "year": 2022
    },
    {
      "lat": 43.0691,
      "lng": 25.2543,
      "year": 2022
    },
    {
      "lat": 42.3952,
      "lng": 26.5103,
      "year": 2022
    },
    {
      "lat": 43.2216,
      "lng": 24.895,
      "year": 2022
    },
    {
      "lat": 41.6162,
      "lng": 25.1359,
      "year": 2022
    },
    {
      "lat": 42.4438,
      "lng": 27.3899,
      "year": 2022
    },
    {
      "lat": 42.6331,
      "lng": 23.4386,
      "year": 2022
    },
    {
      "lat": 42.4675,
      "lng": 24.7972,
      "year": 2022
    },
    {
      "lat": 43.0739,
      "lng": 23.3739,
      "year": 2022
    },
    {
      "lat": 42.7463,
      "lng": 27.6225,
      "year": 2022
    },
    {
      "lat": 42.6156,
      "lng": 23.3573,
      "year": 2022
    },
    {
      "lat": 43.1103,
      "lng": 23.4602,
      "year": 2022
    },
    {
      "lat": 41.8391,
      "lng": 23.4746,
      "year": 2022
    },
    {
      "lat": 43.6291,
      "lng": 27.7149,
      "year": 2022
    },
    {
      "lat": 42.3498,
      "lng": 25.2238,
      "year": 2022
    },
    {
      "lat": 43.1347,
      "lng": 25.3528,
      "year": 2022
    },
    {
      "lat": 42.0971,
      "lng": 27.6867,
      "year": 2022
    },
    {
      "lat": 41.5806,
      "lng": 24.8309,
      "year": 2022
    },
    {
      "lat": 43.0809,
      "lng": 23.3726,
      "year": 2022
    },
    {
      "lat": 42.8238,
      "lng": 25.4456,
      "year": 2022
    },
    {
      "lat": 43.629,
      "lng": 27.7135,
      "year": 2022
    },
    {
      "lat": 42.5572,
      "lng": 23.4242,
      "year": 2022
    },
    {
      "lat": 43.4717,
      "lng": 26.3339,
      "year": 2022
    },
    {
      "lat": 43.2266,
      "lng": 24.3922,
      "year": 2022
    },
    {
      "lat": 42.9104,
      "lng": 27.8474,
      "year": 2022
    },
    {
      "lat": 43.2415,
      "lng": 28.0115,
      "year": 2022
    },
    {
      "lat": 42.9064,
      "lng": 25.9223,
      "year": 2022
    },
    {
      "lat": 42.6953,
      "lng": 26.8172,
      "year": 2022
    },
    {
      "lat": 42.3861,
      "lng": 27.7015,
      "year": 2022
    },
    {
      "lat": 42.9063,
      "lng": 25.9224,
      "year": 2022
    },
    {
      "lat": 42.8496,
      "lng": 25.4679,
      "year": 2022
    },
    {
      "lat": 42.7085,
      "lng": 26.3273,
      "year": 2022
    },
    {
      "lat": 41.6177,
      "lng": 25.0154,
      "year": 2022
    },
    {
      "lat": 42.6522,
      "lng": 23.2594,
      "year": 2022
    },
    {
      "lat": 41.5816,
      "lng": 24.7256,
      "year": 2022
    },
    {
      "lat": 42.5046,
      "lng": 24.3236,
      "year": 2022
    },
    {
      "lat": 43.4163,
      "lng": 28.5059,
      "year": 2022
    },
    {
      "lat": 42.6239,
      "lng": 25.5421,
      "year": 2022
    },
    {
      "lat": 42.8668,
      "lng": 22.6551,
      "year": 2022
    },
    {
      "lat": 41.5181,
      "lng": 24.6414,
      "year": 2022
    },
    {
      "lat": 41.5814,
      "lng": 24.7257,
      "year": 2022
    },
    {
      "lat": 41.5288,
      "lng": 24.9124,
      "year": 2022
    },
    {
      "lat": 43.2776,
      "lng": 28.0162,
      "year": 2022
    },
    {
      "lat": 43.1759,
      "lng": 23.5152,
      "year": 2022
    },
    {
      "lat": 43.2776,
      "lng": 28.0162,
      "year": 2022
    },
    {
      "lat": 42.7269,
      "lng": 23.2491,
      "year": 2021
    },
    {
      "lat": 42.0464,
      "lng": 23.1066,
      "year": 2021
    },
    {
      "lat": 43.1052,
      "lng": 23.4782,
      "year": 2021
    },
    {
      "lat": 43.2893,
      "lng": 26.1868,
      "year": 2021
    },
    {
      "lat": 42.557,
      "lng": 23.424,
      "year": 2021
    },
    {
      "lat": 43.2893,
      "lng": 26.1868,
      "year": 2021
    },
    {
      "lat": 42.85,
      "lng": 27.4547,
      "year": 2021
    },
    {
      "lat": 42.8931,
      "lng": 24.5428,
      "year": 2021
    },
    {
      "lat": 42.8622,
      "lng": 22.702,
      "year": 2021
    },
    {
      "lat": 41.8154,
      "lng": 23.5678,
      "year": 2021
    },
    {
      "lat": 42.4827,
      "lng": 25.549,
      "year": 2021
    },
    {
      "lat": 43.4351,
      "lng": 27.2778,
      "year": 2021
    },
    {
      "lat": 41.6382,
      "lng": 25.328,
      "year": 2021
    },
    {
      "lat": 41.4029,
      "lng": 23.2054,
      "year": 2021
    },
    {
      "lat": 43.4101,
      "lng": 28.1485,
      "year": 2021
    },
    {
      "lat": 41.4029,
      "lng": 23.2054,
      "year": 2021
    },
    {
      "lat": 41.4028,
      "lng": 23.2054,
      "year": 2021
    },
    {
      "lat": 43.4101,
      "lng": 28.1485,
      "year": 2021
    },
    {
      "lat": 42.6904,
      "lng": 23.3395,
      "year": 2021
    },
    {
      "lat": 41.7438,
      "lng": 24.4082,
      "year": 2021
    },
    {
      "lat": 42.6015,
      "lng": 23.3851,
      "year": 2021
    },
    {
      "lat": 43.2273,
      "lng": 28.0033,
      "year": 2021
    },
    {
      "lat": 42.6544,
      "lng": 25.1983,
      "year": 2021
    },
    {
      "lat": 41.8125,
      "lng": 23.5488,
      "year": 2021
    },
    {
      "lat": 43.5414,
      "lng": 28.539,
      "year": 2021
    },
    {
      "lat": 41.6187,
      "lng": 25.1346,
      "year": 2021
    },
    {
      "lat": 42.6159,
      "lng": 23.3096,
      "year": 2021
    },
    {
      "lat": 42.6459,
      "lng": 23.9211,
      "year": 2021
    },
    {
      "lat": 43.277,
      "lng": 28.0156,
      "year": 2021
    },
    {
      "lat": 41.4029,
      "lng": 23.2054,
      "year": 2021
    },
    {
      "lat": 42.9542,
      "lng": 27.7756,
      "year": 2020
    },
    {
      "lat": 42.6043,
      "lng": 23.4139,
      "year": 2020
    },
    {
      "lat": 42.6043,
      "lng": 23.4139,
      "year": 2020
    },
    {
      "lat": 42.5425,
      "lng": 23.1545,
      "year": 2020
    },
    {
      "lat": 42.6043,
      "lng": 23.4139,
      "year": 2020
    },
    {
      "lat": 43.0658,
      "lng": 23.9006,
      "year": 2020
    },
    {
      "lat": 42.9058,
      "lng": 23.5439,
      "year": 2020
    },
    {
      "lat": 42.5925,
      "lng": 23.5124,
      "year": 2020
    },
    {
      "lat": 42.6601,
      "lng": 23.1809,
      "year": 2020
    },
    {
      "lat": 42.0058,
      "lng": 24.8842,
      "year": 2019
    },
    {
      "lat": 42.6778,
      "lng": 23.3461,
      "year": 2019
    },
    {
      "lat": 41.687,
      "lng": 25.2893,
      "year": 2019
    },
    {
      "lat": 43.2756,
      "lng": 27.119,
      "year": 2019
    },
    {
      "lat": 43.0614,
      "lng": 25.2897,
      "year": 2019
    },
    {
      "lat": 43.0842,
      "lng": 25.6733,
      "year": 2019
    },
    {
      "lat": 43.0029,
      "lng": 25.2499,
      "year": 2019
    },
    {
      "lat": 43.0395,
      "lng": 23.3309,
      "year": 2019
    },
    {
      "lat": 43.1,
      "lng": 25.6659,
      "year": 2019
    },
    {
      "lat": 43.0995,
      "lng": 25.6659,
      "year": 2019
    },
    {
      "lat": 43.2177,
      "lng": 27.9894,
      "year": 2019
    },
    {
      "lat": 42.1805,
      "lng": 22.9736,
      "year": 2019
    },
    {
      "lat": 43.0029,
      "lng": 25.2499,
      "year": 2019
    },
    {
      "lat": 43.0842,
      "lng": 25.6733,
      "year": 2019
    },
    {
      "lat": 42.6925,
      "lng": 25.3864,
      "year": 2019
    },
    {
      "lat": 42.5957,
      "lng": 23.4229,
      "year": 2019
    },
    {
      "lat": 42.8541,
      "lng": 25.0939,
      "year": 2019
    },
    {
      "lat": 41.5897,
      "lng": 24.8319,
      "year": 2019
    },
    {
      "lat": 43.5979,
      "lng": 22.7799,
      "year": 2019
    },
    {
      "lat": 43.1737,
      "lng": 27.4463,
      "year": 2019
    },
    {
      "lat": 42.7283,
      "lng": 27.7716,
      "year": 2019
    },
    {
      "lat": 42.6523,
      "lng": 24.7769,
      "year": 2018
    },
    {
      "lat": 42.3151,
      "lng": 27.7353,
      "year": 2018
    },
    {
      "lat": 41.9424,
      "lng": 24.8541,
      "year": 2017
    },
    {
      "lat": 41.5124,
      "lng": 24.661,
      "year": 2017
    },
    {
      "lat": 41.4592,
      "lng": 24.6433,
      "year": 2017
    },
    {
      "lat": 41.6831,
      "lng": 23.8309,
      "year": 2017
    },
    {
      "lat": 42.6127,
      "lng": 23.4176,
      "year": 2017
    },
    {
      "lat": 41.4334,
      "lng": 25.0779,
      "year": 2017
    },
    {
      "lat": 42.5982,
      "lng": 23.4192,
      "year": 2017
    },
    {
      "lat": 42.2784,
      "lng": 27.752,
      "year": 2016
    },
    {
      "lat": 43.7045,
      "lng": 25.9754,
      "year": 2016
    },
    {
      "lat": 43.0333,
      "lng": 23.3402,
      "year": 2015
    },
    {
      "lat": 43.0169,
      "lng": 23.2354,
      "year": 2014
    },
    {
      "lat": 43.6222,
      "lng": 22.6778,
      "year": 2005
    },
    {
      "lat": 42.26,
      "lng": 23.6,
      "year": 2004
    },
    {
      "lat": 41.9861,
      "lng": 24.88,
      "year": 2004
    },
    {
      "lat": 42.6697,
      "lng": 27.5797,
      "year": 1999
    },
    {
      "lat": 42.6164,
      "lng": 27.2258,
      "year": 1999
    },
    {
      "lat": 42.2992,
      "lng": 27.7483,
      "year": 1999
    },
    {
      "lat": 43.4169,
      "lng": 27.9817,
      "year": 1999
    },
    {
      "lat": 41.9769,
      "lng": 27.5159,
      "year": 1957
    },
    {
      "lat": 43.0811,
      "lng": 25.6292,
      "year": 1922
    },
    {
      "lat": 43.08,
      "lng": 25.6308,
      "year": 1922
    }
  ],
  "bulgaria_total_count": 178,
  "bulgaria_accessed": "2026-05-16"
}