{
  "slug": "hyssopus-officinalis",
  "taxon_key": 5341387,
  "taxon_name": "Hyssopus officinalis L.",
  "total_count_in_europe": 15290,
  "points_sampled": 300,
  "points": [
    {
      "lat": 56.5412,
      "lng": 16.4385,
      "country": "SE",
      "year": 2026
    },
    {
      "lat": 57.5507,
      "lng": 18.2031,
      "country": "SE",
      "year": 2026
    },
    {
      "lat": 55.6679,
      "lng": 12.5429,
      "country": "DK",
      "year": 2026
    },
    {
      "lat": 51.4938,
      "lng": -0.0472,
      "country": "GB",
      "year": 2026
    },
    {
      "lat": 55.7228,
      "lng": 13.1845,
      "country": "SE",
      "year": 2026
    },
    {
      "lat": 59.6661,
      "lng": 10.7759,
      "country": "NO",
      "year": 2026
    },
    {
      "lat": 56.6742,
      "lng": 16.5483,
      "country": "SE",
      "year": 2026
    },
    {
      "lat": 50.2919,
      "lng": 13.9176,
      "country": "CZ",
      "year": 2026
    },
    {
      "lat": 59.8104,
      "lng": 17.6623,
      "country": "SE",
      "year": 2025
    },
    {
      "lat": 46.1184,
      "lng": 7.0829,
      "country": "CH",
      "year": 2025
    },
    {
      "lat": 46.1632,
      "lng": 7.0179,
      "country": "CH",
      "year": 2025
    },
    {
      "lat": 46.2539,
      "lng": 7.3414,
      "country": "CH",
      "year": 2025
    },
    {
      "lat": 46.2088,
      "lng": 7.2767,
      "country": "CH",
      "year": 2025
    },
    {
      "lat": 46.2539,
      "lng": 7.3414,
      "country": "CH",
      "year": 2025
    },
    {
      "lat": 46.2539,
      "lng": 7.3414,
      "country": "CH",
      "year": 2025
    },
    {
      "lat": 46.2539,
      "lng": 7.3414,
      "country": "CH",
      "year": 2025
    },
    {
      "lat": 46.2088,
      "lng": 7.2767,
      "country": "CH",
      "year": 2025
    },
    {
      "lat": 46.2539,
      "lng": 7.3414,
      "country": "CH",
      "year": 2025
    },
    {
      "lat": 43.559,
      "lng": 4.083,
      "country": "FR",
      "year": 2025
    },
    {
      "lat": 48.8397,
      "lng": 2.4419,
      "country": "FR",
      "year": 2025
    },
    {
      "lat": 43.5586,
      "lng": 4.084,
      "country": "FR",
      "year": 2025
    },
    {
      "lat": 48.8397,
      "lng": 2.4419,
      "country": "FR",
      "year": 2025
    },
    {
      "lat": 46.1186,
      "lng": 7.1476,
      "country": "CH",
      "year": 2025
    },
    {
      "lat": 46.1186,
      "lng": 7.1476,
      "country": "CH",
      "year": 2025
    },
    {
      "lat": 46.1184,
      "lng": 7.0829,
      "country": "CH",
      "year": 2025
    },
    {
      "lat": 46.1636,
      "lng": 7.1474,
      "country": "CH",
      "year": 2025
    },
    {
      "lat": 46.1636,
      "lng": 7.1474,
      "country": "CH",
      "year": 2025
    },
    {
      "lat": 46.1636,
      "lng": 7.1474,
      "country": "CH",
      "year": 2025
    },
    {
      "lat": 46.1186,
      "lng": 7.1476,
      "country": "CH",
      "year": 2025
    },
    {
      "lat": 46.1184,
      "lng": 7.0829,
      "country": "CH",
      "year": 2025
    },
    {
      "lat": 46.2089,
      "lng": 7.3415,
      "country": "CH",
      "year": 2025
    },
    {
      "lat": 46.2089,
      "lng": 7.3415,
      "country": "CH",
      "year": 2025
    },
    {
      "lat": 46.2082,
      "lng": 7.8597,
      "country": "CH",
      "year": 2025
    },
    {
      "lat": 46.2539,
      "lng": 7.3414,
      "country": "CH",
      "year": 2025
    },
    {
      "lat": 46.2539,
      "lng": 7.3414,
      "country": "CH",
      "year": 2025
    },
    {
      "lat": 46.2979,
      "lng": 7.9253,
      "country": "CH",
      "year": 2025
    },
    {
      "lat": 46.2531,
      "lng": 7.8601,
      "country": "CH",
      "year": 2025
    },
    {
      "lat": 46.2531,
      "lng": 7.8601,
      "country": "CH",
      "year": 2025
    },
    {
      "lat": 46.2088,
      "lng": 7.2767,
      "country": "CH",
      "year": 2025
    },
    {
      "lat": 46.2088,
      "lng": 7.2767,
      "country": "CH",
      "year": 2025
    },
    {
      "lat": 46.2088,
      "lng": 7.2767,
      "country": "CH",
      "year": 2025
    },
    {
      "lat": 46.2089,
      "lng": 7.3415,
      "country": "CH",
      "year": 2025
    },
    {
      "lat": 46.2989,
      "lng": 7.536,
      "country": "CH",
      "year": 2025
    },
    {
      "lat": 46.2531,
      "lng": 7.8601,
      "country": "CH",
      "year": 2025
    },
    {
      "lat": 46.2531,
      "lng": 7.8601,
      "country": "CH",
      "year": 2025
    },
    {
      "lat": 46.2089,
      "lng": 7.3415,
      "country": "CH",
      "year": 2025
    },
    {
      "lat": 46.2531,
      "lng": 7.8601,
      "country": "CH",
      "year": 2025
    },
    {
      "lat": 46.2088,
      "lng": 7.2767,
      "country": "CH",
      "year": 2025
    },
    {
      "lat": 50.9032,
      "lng": 4.8865,
      "country": "BE",
      "year": 2025
    },
    {
      "lat": 56.6741,
      "lng": 16.5488,
      "country": "SE",
      "year": 2025
    },
    {
      "lat": 50.1814,
      "lng": 41.9883,
      "country": "RU",
      "year": 2025
    },
    {
      "lat": 47.7649,
      "lng": 8.8194,
      "country": "DE",
      "year": 2025
    },
    {
      "lat": 49.5199,
      "lng": 41.0825,
      "country": "RU",
      "year": 2025
    },
    {
      "lat": 49.52,
      "lng": 41.085,
      "country": "RU",
      "year": 2025
    },
    {
      "lat": 46.2089,
      "lng": 7.3415,
      "country": "CH",
      "year": 2025
    },
    {
      "lat": 50.8665,
      "lng": 4.309,
      "country": "BE",
      "year": 2025
    },
    {
      "lat": 56.5377,
      "lng": 16.445,
      "country": "SE",
      "year": 2025
    },
    {
      "lat": 50.7829,
      "lng": 41.9121,
      "country": "RU",
      "year": 2025
    },
    {
      "lat": 50.0168,
      "lng": 42.3915,
      "country": "RU",
      "year": 2025
    },
    {
      "lat": 58.6178,
      "lng": 13.3973,
      "country": "SE",
      "year": 2025
    },
    {
      "lat": 46.2539,
      "lng": 7.5359,
      "country": "CH",
      "year": 2025
    },
    {
      "lat": 46.2531,
      "lng": 7.8601,
      "country": "CH",
      "year": 2025
    },
    {
      "lat": 46.2531,
      "lng": 7.8601,
      "country": "CH",
      "year": 2025
    },
    {
      "lat": 46.1638,
      "lng": 7.2121,
      "country": "CH",
      "year": 2025
    },
    {
      "lat": 46.1184,
      "lng": 7.0829,
      "country": "CH",
      "year": 2025
    },
    {
      "lat": 46.2539,
      "lng": 7.3414,
      "country": "CH",
      "year": 2025
    },
    {
      "lat": 46.1184,
      "lng": 7.0829,
      "country": "CH",
      "year": 2025
    },
    {
      "lat": 46.2531,
      "lng": 7.8601,
      "country": "CH",
      "year": 2025
    },
    {
      "lat": 46.1184,
      "lng": 7.0829,
      "country": "CH",
      "year": 2025
    },
    {
      "lat": 46.2979,
      "lng": 7.9253,
      "country": "CH",
      "year": 2025
    },
    {
      "lat": 46.7934,
      "lng": 7.6678,
      "country": "CH",
      "year": 2025
    },
    {
      "lat": 46.2531,
      "lng": 7.8601,
      "country": "CH",
      "year": 2025
    },
    {
      "lat": 46.2539,
      "lng": 7.3414,
      "country": "CH",
      "year": 2025
    },
    {
      "lat": 46.2539,
      "lng": 7.5359,
      "country": "CH",
      "year": 2025
    },
    {
      "lat": 49.9865,
      "lng": 42.3525,
      "country": "RU",
      "year": 2025
    },
    {
      "lat": 49.9852,
      "lng": 42.3504,
      "country": "RU",
      "year": 2025
    },
    {
      "lat": 50.0272,
      "lng": 42.4076,
      "country": "RU",
      "year": 2025
    },
    {
      "lat": 49.9668,
      "lng": 42.3297,
      "country": "RU",
      "year": 2025
    },
    {
      "lat": 50.9154,
      "lng": 3.5371,
      "country": "BE",
      "year": 2025
    },
    {
      "lat": 51.3,
      "lng": 6.1,
      "country": "NL",
      "year": 2025
    },
    {
      "lat": 59.3794,
      "lng": 16.4779,
      "country": "SE",
      "year": 2025
    },
    {
      "lat": 52.05,
      "lng": 5.1,
      "country": "NL",
      "year": 2025
    },
    {
      "lat": 52.0,
      "lng": 6.2,
      "country": "NL",
      "year": 2025
    },
    {
      "lat": 55.4714,
      "lng": 13.0098,
      "country": "SE",
      "year": 2025
    },
    {
      "lat": 55.7009,
      "lng": 13.2182,
      "country": "SE",
      "year": 2025
    },
    {
      "lat": 46.2088,
      "lng": 7.2767,
      "country": "CH",
      "year": 2025
    },
    {
      "lat": 55.4675,
      "lng": 13.0091,
      "country": "SE",
      "year": 2025
    },
    {
      "lat": 46.2539,
      "lng": 7.4062,
      "country": "CH",
      "year": 2025
    },
    {
      "lat": 46.1636,
      "lng": 7.1474,
      "country": "CH",
      "year": 2025
    },
    {
      "lat": 47.4175,
      "lng": 8.5982,
      "country": "CH",
      "year": 2025
    },
    {
      "lat": 50.5523,
      "lng": 40.3884,
      "country": "RU",
      "year": 2025
    },
    {
      "lat": 59.906,
      "lng": 10.7359,
      "country": "NO",
      "year": 2025
    },
    {
      "lat": 52.55,
      "lng": 5.35,
      "country": "NL",
      "year": 2025
    },
    {
      "lat": 59.8974,
      "lng": 10.622,
      "country": "NO",
      "year": 2025
    },
    {
      "lat": 56.7558,
      "lng": 12.9054,
      "country": "SE",
      "year": 2025
    },
    {
      "lat": 55.5824,
      "lng": 13.0154,
      "country": "SE",
      "year": 2025
    },
    {
      "lat": 55.4673,
      "lng": 13.0092,
      "country": "SE",
      "year": 2025
    },
    {
      "lat": 58.8329,
      "lng": 17.5021,
      "country": "SE",
      "year": 2025
    },
    {
      "lat": 59.5266,
      "lng": 17.9582,
      "country": "SE",
      "year": 2025
    },
    {
      "lat": 49.8929,
      "lng": 40.1742,
      "country": "RU",
      "year": 2025
    },
    {
      "lat": 49.8933,
      "lng": 40.1739,
      "country": "RU",
      "year": 2025
    },
    {
      "lat": 49.8932,
      "lng": 40.1741,
      "country": "RU",
      "year": 2025
    },
    {
      "lat": 49.8929,
      "lng": 40.1742,
      "country": "RU",
      "year": 2025
    },
    {
      "lat": 49.9785,
      "lng": 38.9977,
      "country": "RU",
      "year": 2025
    },
    {
      "lat": 49.7381,
      "lng": 39.1234,
      "country": "UA",
      "year": 2025
    },
    {
      "lat": 52.05,
      "lng": 5.05,
      "country": "NL",
      "year": 2025
    },
    {
      "lat": 51.95,
      "lng": 5.65,
      "country": "NL",
      "year": 2025
    },
    {
      "lat": 52.0,
      "lng": 6.2,
      "country": "NL",
      "year": 2025
    },
    {
      "lat": 52.55,
      "lng": 5.35,
      "country": "NL",
      "year": 2025
    },
    {
      "lat": 52.05,
      "lng": 4.3,
      "country": "NL",
      "year": 2025
    },
    {
      "lat": 50.5105,
      "lng": 40.0069,
      "country": "RU",
      "year": 2025
    },
    {
      "lat": 50.5106,
      "lng": 40.0073,
      "country": "RU",
      "year": 2025
    },
    {
      "lat": 50.5104,
      "lng": 40.0064,
      "country": "RU",
      "year": 2025
    },
    {
      "lat": 50.5108,
      "lng": 40.0077,
      "country": "RU",
      "year": 2025
    },
    {
      "lat": 50.5104,
      "lng": 40.0062,
      "country": "RU",
      "year": 2025
    },
    {
      "lat": 50.5109,
      "lng": 40.0076,
      "country": "RU",
      "year": 2025
    },
    {
      "lat": 50.8564,
      "lng": 6.1569,
      "country": "DE",
      "year": 2025
    },
    {
      "lat": 40.3861,
      "lng": 39.1281,
      "country": "TR",
      "year": 2025
    },
    {
      "lat": 63.6623,
      "lng": 22.6975,
      "country": "FI",
      "year": 2025
    },
    {
      "lat": 46.2082,
      "lng": 7.8597,
      "country": "CH",
      "year": 2025
    },
    {
      "lat": 46.2987,
      "lng": 7.6658,
      "country": "CH",
      "year": 2025
    },
    {
      "lat": 46.2531,
      "lng": 7.8601,
      "country": "CH",
      "year": 2025
    },
    {
      "lat": 46.2088,
      "lng": 7.2767,
      "country": "CH",
      "year": 2025
    },
    {
      "lat": 47.1534,
      "lng": 7.2738,
      "country": "CH",
      "year": 2025
    },
    {
      "lat": 55.5941,
      "lng": 13.1285,
      "country": "SE",
      "year": 2025
    },
    {
      "lat": 55.7201,
      "lng": 13.239,
      "country": "SE",
      "year": 2025
    },
    {
      "lat": 51.9588,
      "lng": 8.384,
      "country": "DE",
      "year": 2025
    },
    {
      "lat": 43.1071,
      "lng": 43.4275,
      "country": "RU",
      "year": 2025
    },
    {
      "lat": 52.0043,
      "lng": 8.5367,
      "country": "DE",
      "year": 2025
    },
    {
      "lat": 49.8987,
      "lng": 39.3997,
      "country": "RU",
      "year": 2025
    },
    {
      "lat": 55.4715,
      "lng": 13.0097,
      "country": "SE",
      "year": 2025
    },
    {
      "lat": 50.3571,
      "lng": 4.9154,
      "country": "BE",
      "year": 2025
    },
    {
      "lat": 54.6579,
      "lng": 11.3597,
      "country": "DK",
      "year": 2025
    },
    {
      "lat": 50.5432,
      "lng": 39.9614,
      "country": "RU",
      "year": 2025
    },
    {
      "lat": 51.1967,
      "lng": 4.3625,
      "country": "BE",
      "year": 2025
    },
    {
      "lat": 50.7789,
      "lng": 4.3291,
      "country": "BE",
      "year": 2025
    },
    {
      "lat": 59.8982,
      "lng": 10.6229,
      "country": "NO",
      "year": 2025
    },
    {
      "lat": 59.8979,
      "lng": 10.6236,
      "country": "NO",
      "year": 2025
    },
    {
      "lat": 51.2056,
      "lng": 4.4258,
      "country": "BE",
      "year": 2025
    },
    {
      "lat": 50.8564,
      "lng": 6.1569,
      "country": "DE",
      "year": 2025
    },
    {
      "lat": 48.0791,
      "lng": 11.6156,
      "country": "DE",
      "year": 2025
    },
    {
      "lat": 51.5838,
      "lng": -0.0003,
      "country": "GB",
      "year": 2025
    },
    {
      "lat": 48.9461,
      "lng": 43.8215,
      "country": "RU",
      "year": 2025
    },
    {
      "lat": 45.7329,
      "lng": 4.857,
      "country": "FR",
      "year": 2025
    },
    {
      "lat": 46.1184,
      "lng": 7.0829,
      "country": "CH",
      "year": 2025
    },
    {
      "lat": 46.1184,
      "lng": 7.0829,
      "country": "CH",
      "year": 2025
    },
    {
      "lat": 46.1184,
      "lng": 7.0829,
      "country": "CH",
      "year": 2025
    },
    {
      "lat": 46.1184,
      "lng": 7.0829,
      "country": "CH",
      "year": 2025
    },
    {
      "lat": 46.1184,
      "lng": 7.0829,
      "country": "CH",
      "year": 2025
    },
    {
      "lat": 46.2087,
      "lng": 7.2119,
      "country": "CH",
      "year": 2025
    },
    {
      "lat": 46.6073,
      "lng": 6.2312,
      "country": "CH",
      "year": 2025
    },
    {
      "lat": 46.2539,
      "lng": 7.4062,
      "country": "CH",
      "year": 2025
    },
    {
      "lat": 59.5266,
      "lng": 17.9582,
      "country": "SE",
      "year": 2025
    },
    {
      "lat": 58.2961,
      "lng": 14.7112,
      "country": "SE",
      "year": 2025
    },
    {
      "lat": 55.5213,
      "lng": 12.9954,
      "country": "SE",
      "year": 2025
    },
    {
      "lat": 58.5565,
      "lng": 12.3576,
      "country": "SE",
      "year": 2025
    },
    {
      "lat": 52.55,
      "lng": 5.35,
      "country": "NL",
      "year": 2025
    },
    {
      "lat": 52.55,
      "lng": 5.35,
      "country": "NL",
      "year": 2025
    },
    {
      "lat": 52.55,
      "lng": 5.35,
      "country": "NL",
      "year": 2025
    },
    {
      "lat": 50.9368,
      "lng": 4.6528,
      "country": "BE",
      "year": 2025
    },
    {
      "lat": 51.0252,
      "lng": 3.6909,
      "country": "BE",
      "year": 2025
    },
    {
      "lat": 59.2186,
      "lng": 17.9317,
      "country": "SE",
      "year": 2025
    },
    {
      "lat": 42.4694,
      "lng": 2.0822,
      "country": "FR",
      "year": 2025
    },
    {
      "lat": 40.319,
      "lng": -1.3243,
      "country": "ES",
      "year": 2025
    },
    {
      "lat": 49.1969,
      "lng": 43.6143,
      "country": "RU",
      "year": 2025
    },
    {
      "lat": 49.1155,
      "lng": 43.5396,
      "country": "RU",
      "year": 2025
    },
    {
      "lat": 45.7178,
      "lng": 7.3144,
      "country": "IT",
      "year": 2025
    },
    {
      "lat": 48.9475,
      "lng": 43.6165,
      "country": "RU",
      "year": 2025
    },
    {
      "lat": 49.0966,
      "lng": 43.4429,
      "country": "RU",
      "year": 2025
    },
    {
      "lat": 51.0253,
      "lng": 7.0779,
      "country": "DE",
      "year": 2025
    },
    {
      "lat": 48.9698,
      "lng": 43.6152,
      "country": "RU",
      "year": 2025
    },
    {
      "lat": 49.0327,
      "lng": 43.5813,
      "country": "RU",
      "year": 2025
    },
    {
      "lat": 52.55,
      "lng": 5.35,
      "country": "NL",
      "year": 2025
    },
    {
      "lat": 52.55,
      "lng": 5.35,
      "country": "NL",
      "year": 2025
    },
    {
      "lat": 52.55,
      "lng": 5.35,
      "country": "NL",
      "year": 2025
    },
    {
      "lat": 48.9557,
      "lng": 43.852,
      "country": "RU",
      "year": 2025
    },
    {
      "lat": 48.9948,
      "lng": 43.9089,
      "country": "RU",
      "year": 2025
    },
    {
      "lat": 49.0143,
      "lng": 43.572,
      "country": "RU",
      "year": 2025
    },
    {
      "lat": 48.9474,
      "lng": 43.6165,
      "country": "RU",
      "year": 2025
    },
    {
      "lat": 53.3481,
      "lng": 34.2158,
      "country": "RU",
      "year": 2025
    },
    {
      "lat": 49.1398,
      "lng": 43.4275,
      "country": "RU",
      "year": 2025
    },
    {
      "lat": 41.6958,
      "lng": 44.7413,
      "country": "GE",
      "year": 2025
    },
    {
      "lat": 42.2224,
      "lng": 1.5749,
      "country": "ES",
      "year": 2025
    },
    {
      "lat": 52.05,
      "lng": 4.4,
      "country": "NL",
      "year": 2025
    },
    {
      "lat": 52.05,
      "lng": 4.4,
      "country": "NL",
      "year": 2025
    },
    {
      "lat": 52.05,
      "lng": 4.4,
      "country": "NL",
      "year": 2025
    },
    {
      "lat": 44.7854,
      "lng": 6.8684,
      "country": "FR",
      "year": 2025
    },
    {
      "lat": 50.4112,
      "lng": 40.9939,
      "country": "RU",
      "year": 2025
    },
    {
      "lat": 50.4093,
      "lng": 40.9972,
      "country": "RU",
      "year": 2025
    },
    {
      "lat": 50.4755,
      "lng": 41.3464,
      "country": "RU",
      "year": 2025
    },
    {
      "lat": 56.6311,
      "lng": 12.9477,
      "country": "SE",
      "year": 2025
    },
    {
      "lat": 49.8988,
      "lng": 39.3996,
      "country": "RU",
      "year": 2025
    },
    {
      "lat": 49.899,
      "lng": 39.3997,
      "country": "RU",
      "year": 2025
    },
    {
      "lat": 46.2088,
      "lng": 7.2767,
      "country": "CH",
      "year": 2025
    },
    {
      "lat": 46.1639,
      "lng": 7.3415,
      "country": "CH",
      "year": 2025
    },
    {
      "lat": 44.6472,
      "lng": 6.6322,
      "country": "FR",
      "year": 2025
    },
    {
      "lat": 45.036,
      "lng": 6.4004,
      "country": "FR",
      "year": 2025
    },
    {
      "lat": 58.6027,
      "lng": 13.404,
      "country": "SE",
      "year": 2025
    },
    {
      "lat": 50.7789,
      "lng": 4.3291,
      "country": "BE",
      "year": 2025
    },
    {
      "lat": 50.9842,
      "lng": -0.3546,
      "country": "GB",
      "year": 2025
    },
    {
      "lat": 57.5399,
      "lng": 18.2543,
      "country": "SE",
      "year": 2025
    },
    {
      "lat": 59.0458,
      "lng": 16.8004,
      "country": "SE",
      "year": 2025
    },
    {
      "lat": 58.6016,
      "lng": 16.2091,
      "country": "SE",
      "year": 2025
    },
    {
      "lat": 50.8564,
      "lng": 6.1569,
      "country": "DE",
      "year": 2025
    },
    {
      "lat": 59.0583,
      "lng": 17.3064,
      "country": "SE",
      "year": 2025
    },
    {
      "lat": 42.0066,
      "lng": 13.9987,
      "country": "IT",
      "year": 2025
    },
    {
      "lat": 42.4686,
      "lng": 2.0832,
      "country": "FR",
      "year": 2025
    },
    {
      "lat": 50.2557,
      "lng": 42.0043,
      "country": "RU",
      "year": 2025
    },
    {
      "lat": 50.2554,
      "lng": 42.0051,
      "country": "RU",
      "year": 2025
    },
    {
      "lat": 42.108,
      "lng": 1.6081,
      "country": "ES",
      "year": 2025
    },
    {
      "lat": 52.0,
      "lng": 4.35,
      "country": "NL",
      "year": 2025
    },
    {
      "lat": 52.0,
      "lng": 4.35,
      "country": "NL",
      "year": 2025
    },
    {
      "lat": 41.7163,
      "lng": -4.5552,
      "country": "ES",
      "year": 2025
    },
    {
      "lat": 52.15,
      "lng": 5.35,
      "country": "NL",
      "year": 2025
    },
    {
      "lat": 42.108,
      "lng": 1.6081,
      "country": "ES",
      "year": 2025
    },
    {
      "lat": 44.9365,
      "lng": 5.9761,
      "country": "FR",
      "year": 2025
    },
    {
      "lat": 42.1003,
      "lng": 1.4451,
      "country": "ES",
      "year": 2025
    },
    {
      "lat": 44.6188,
      "lng": 6.5588,
      "country": "FR",
      "year": 2025
    },
    {
      "lat": 41.8518,
      "lng": 0.7789,
      "country": "ES",
      "year": 2025
    },
    {
      "lat": 41.6998,
      "lng": 44.7824,
      "country": "GE",
      "year": 2025
    },
    {
      "lat": 41.6884,
      "lng": 44.8041,
      "country": "GE",
      "year": 2025
    },
    {
      "lat": 42.464,
      "lng": 19.8911,
      "country": "AL",
      "year": 2025
    },
    {
      "lat": 41.6871,
      "lng": 44.7976,
      "country": "GE",
      "year": 2025
    },
    {
      "lat": 52.3,
      "lng": 4.8,
      "country": "NL",
      "year": 2025
    },
    {
      "lat": 52.3,
      "lng": 4.8,
      "country": "NL",
      "year": 2025
    },
    {
      "lat": 52.3,
      "lng": 4.8,
      "country": "NL",
      "year": 2025
    },
    {
      "lat": 59.2532,
      "lng": 15.2069,
      "country": "SE",
      "year": 2025
    },
    {
      "lat": 55.4686,
      "lng": 13.0095,
      "country": "SE",
      "year": 2025
    },
    {
      "lat": 59.2349,
      "lng": 15.2264,
      "country": "SE",
      "year": 2025
    },
    {
      "lat": 55.4675,
      "lng": 13.0095,
      "country": "SE",
      "year": 2025
    },
    {
      "lat": 44.2788,
      "lng": 15.5586,
      "country": "HR",
      "year": 2025
    },
    {
      "lat": 45.091,
      "lng": 13.7767,
      "country": "HR",
      "year": 2025
    },
    {
      "lat": 47.5802,
      "lng": 3.7697,
      "country": "FR",
      "year": 2025
    },
    {
      "lat": 59.0585,
      "lng": 17.3063,
      "country": "SE",
      "year": 2025
    },
    {
      "lat": 41.5333,
      "lng": 1.6278,
      "country": "ES",
      "year": 2025
    },
    {
      "lat": 39.5349,
      "lng": -1.4407,
      "country": "ES",
      "year": 2025
    },
    {
      "lat": 52.3,
      "lng": 5.05,
      "country": "NL",
      "year": 2025
    },
    {
      "lat": 59.6662,
      "lng": 10.7759,
      "country": "NO",
      "year": 2025
    },
    {
      "lat": 59.8902,
      "lng": 10.6939,
      "country": "NO",
      "year": 2025
    },
    {
      "lat": 59.8601,
      "lng": 10.8518,
      "country": "NO",
      "year": 2025
    },
    {
      "lat": 51.197,
      "lng": 11.7495,
      "country": "DE",
      "year": 2025
    },
    {
      "lat": 53.5877,
      "lng": 10.1385,
      "country": "DE",
      "year": 2025
    },
    {
      "lat": 59.8981,
      "lng": 10.6234,
      "country": "NO",
      "year": 2025
    },
    {
      "lat": 46.2539,
      "lng": 7.4062,
      "country": "CH",
      "year": 2025
    },
    {
      "lat": 46.2539,
      "lng": 7.3414,
      "country": "CH",
      "year": 2025
    },
    {
      "lat": 46.2985,
      "lng": 7.7307,
      "country": "CH",
      "year": 2025
    },
    {
      "lat": 46.2987,
      "lng": 7.6658,
      "country": "CH",
      "year": 2025
    },
    {
      "lat": 46.2987,
      "lng": 7.6658,
      "country": "CH",
      "year": 2025
    },
    {
      "lat": 47.3732,
      "lng": 8.531,
      "country": "CH",
      "year": 2025
    },
    {
      "lat": 46.2987,
      "lng": 7.6658,
      "country": "CH",
      "year": 2025
    },
    {
      "lat": 46.2987,
      "lng": 7.6658,
      "country": "CH",
      "year": 2025
    },
    {
      "lat": 46.2987,
      "lng": 7.6658,
      "country": "CH",
      "year": 2025
    },
    {
      "lat": 46.2088,
      "lng": 7.2767,
      "country": "CH",
      "year": 2025
    },
    {
      "lat": 46.1184,
      "lng": 7.0829,
      "country": "CH",
      "year": 2025
    },
    {
      "lat": 46.2539,
      "lng": 7.3414,
      "country": "CH",
      "year": 2025
    },
    {
      "lat": 46.2089,
      "lng": 7.3415,
      "country": "CH",
      "year": 2025
    },
    {
      "lat": 46.2539,
      "lng": 7.4062,
      "country": "CH",
      "year": 2025
    },
    {
      "lat": 46.2987,
      "lng": 7.6658,
      "country": "CH",
      "year": 2025
    },
    {
      "lat": 46.2089,
      "lng": 7.3415,
      "country": "CH",
      "year": 2025
    },
    {
      "lat": 41.8195,
      "lng": 43.3165,
      "country": "GE",
      "year": 2025
    },
    {
      "lat": 44.6865,
      "lng": 6.6059,
      "country": "FR",
      "year": 2025
    },
    {
      "lat": 44.9421,
      "lng": 5.9959,
      "country": "FR",
      "year": 2025
    },
    {
      "lat": 45.3325,
      "lng": 6.3352,
      "country": "FR",
      "year": 2025
    },
    {
      "lat": 58.6183,
      "lng": 13.3976,
      "country": "SE",
      "year": 2025
    },
    {
      "lat": 45.9217,
      "lng": 10.8873,
      "country": "IT",
      "year": 2025
    },
    {
      "lat": 42.5506,
      "lng": 1.3263,
      "country": "ES",
      "year": 2025
    },
    {
      "lat": 44.71,
      "lng": 6.5909,
      "country": "FR",
      "year": 2025
    },
    {
      "lat": 52.1651,
      "lng": 10.3077,
      "country": "DE",
      "year": 2025
    },
    {
      "lat": 51.5,
      "lng": 5.25,
      "country": "NL",
      "year": 2025
    },
    {
      "lat": 43.5823,
      "lng": 16.5667,
      "country": "HR",
      "year": 2025
    },
    {
      "lat": 41.7974,
      "lng": 44.6349,
      "country": "GE",
      "year": 2025
    },
    {
      "lat": 42.0302,
      "lng": 2.3156,
      "country": "ES",
      "year": 2025
    },
    {
      "lat": 59.81,
      "lng": 17.6643,
      "country": "SE",
      "year": 2025
    },
    {
      "lat": 57.7967,
      "lng": 18.819,
      "country": "SE",
      "year": 2025
    },
    {
      "lat": 50.8606,
      "lng": 4.3822,
      "country": "BE",
      "year": 2025
    },
    {
      "lat": 41.6402,
      "lng": 44.692,
      "country": "GE",
      "year": 2025
    },
    {
      "lat": 42.3108,
      "lng": 2.6445,
      "country": "ES",
      "year": 2025
    },
    {
      "lat": 41.7351,
      "lng": 42.8359,
      "country": "GE",
      "year": 2025
    },
    {
      "lat": 47.8205,
      "lng": 35.0752,
      "country": "UA",
      "year": 2025
    },
    {
      "lat": 42.3266,
      "lng": 13.6962,
      "country": "IT",
      "year": 2025
    },
    {
      "lat": 44.4586,
      "lng": 6.1704,
      "country": "FR",
      "year": 2025
    },
    {
      "lat": 46.2531,
      "lng": 7.8601,
      "country": "CH",
      "year": 2025
    },
    {
      "lat": 46.2531,
      "lng": 7.8601,
      "country": "CH",
      "year": 2025
    },
    {
      "lat": 46.2531,
      "lng": 7.8601,
      "country": "CH",
      "year": 2025
    },
    {
      "lat": 46.2531,
      "lng": 7.8601,
      "country": "CH",
      "year": 2025
    },
    {
      "lat": 46.2531,
      "lng": 7.8601,
      "country": "CH",
      "year": 2025
    },
    {
      "lat": 46.2531,
      "lng": 7.8601,
      "country": "CH",
      "year": 2025
    },
    {
      "lat": 46.0732,
      "lng": 7.0186,
      "country": "CH",
      "year": 2025
    },
    {
      "lat": 46.2531,
      "lng": 7.8601,
      "country": "CH",
      "year": 2025
    },
    {
      "lat": 46.2531,
      "lng": 7.8601,
      "country": "CH",
      "year": 2025
    },
    {
      "lat": 46.2531,
      "lng": 7.8601,
      "country": "CH",
      "year": 2025
    },
    {
      "lat": 46.2531,
      "lng": 7.8601,
      "country": "CH",
      "year": 2025
    },
    {
      "lat": 46.2531,
      "lng": 7.8601,
      "country": "CH",
      "year": 2025
    },
    {
      "lat": 46.2531,
      "lng": 7.8601,
      "country": "CH",
      "year": 2025
    },
    {
      "lat": 46.2531,
      "lng": 7.8601,
      "country": "CH",
      "year": 2025
    },
    {
      "lat": 46.0732,
      "lng": 7.0186,
      "country": "CH",
      "year": 2025
    },
    {
      "lat": 46.2531,
      "lng": 7.8601,
      "country": "CH",
      "year": 2025
    },
    {
      "lat": 46.2531,
      "lng": 7.8601,
      "country": "CH",
      "year": 2025
    },
    {
      "lat": 46.2531,
      "lng": 7.8601,
      "country": "CH",
      "year": 2025
    },
    {
      "lat": 41.7983,
      "lng": 44.6379,
      "country": "GE",
      "year": 2025
    }
  ],
  "source": "GBIF.org occurrence search API",
  "source_url": "https://www.gbif.org/species/5341387",
  "accessed": "2026-05-16",
  "bulgaria_points": [
    {
      "lat": 42.5413,
      "lng": 25.9987,
      "year": 2022
    },
    {
      "lat": 43.1004,
      "lng": 25.6665,
      "year": 2022
    },
    {
      "lat": 42.5804,
      "lng": 22.5776,
      "year": 2021
    },
    {
      "lat": 42.2519,
      "lng": 23.3042,
      "year": 2013
    },
    {
      "lat": 42.4973,
      "lng": 23.1921,
      "year": 2010
    },
    {
      "lat": 43.5611,
      "lng": 22.6444,
      "year": 2005
    },
    {
      "lat": 43.6278,
      "lng": 22.6829,
      "year": 1932
    }
  ],
  "bulgaria_total_count": 7,
  "bulgaria_accessed": "2026-05-16"
}