{
  "slug": "verbascum-densiflorum",
  "taxon_key": 3171939,
  "taxon_name": "Verbascum densiflorum Bertol.",
  "total_count_in_europe": 34453,
  "points_sampled": 300,
  "points": [
    {
      "lat": 47.4868,
      "lng": 9.7595,
      "country": "AT",
      "year": 2026
    },
    {
      "lat": 43.923,
      "lng": 15.1322,
      "country": "HR",
      "year": 2026
    },
    {
      "lat": 43.923,
      "lng": 15.132,
      "country": "HR",
      "year": 2026
    },
    {
      "lat": 48.9469,
      "lng": 17.3774,
      "country": "CZ",
      "year": 2026
    },
    {
      "lat": 43.9221,
      "lng": 15.131,
      "country": "HR",
      "year": 2026
    },
    {
      "lat": 55.7658,
      "lng": 12.4766,
      "country": "DK",
      "year": 2025
    },
    {
      "lat": 52.4,
      "lng": 6.65,
      "country": "NL",
      "year": 2025
    },
    {
      "lat": 51.75,
      "lng": 5.85,
      "country": "NL",
      "year": 2025
    },
    {
      "lat": 44.0197,
      "lng": 4.6591,
      "country": "FR",
      "year": 2025
    },
    {
      "lat": 43.7276,
      "lng": 7.1961,
      "country": "FR",
      "year": 2025
    },
    {
      "lat": 49.3508,
      "lng": 8.6387,
      "country": "DE",
      "year": 2025
    },
    {
      "lat": 49.1096,
      "lng": 8.2735,
      "country": "DE",
      "year": 2025
    },
    {
      "lat": 46.1554,
      "lng": 6.0471,
      "country": "CH",
      "year": 2025
    },
    {
      "lat": 46.1554,
      "lng": 6.0471,
      "country": "CH",
      "year": 2025
    },
    {
      "lat": 46.1554,
      "lng": 6.0471,
      "country": "CH",
      "year": 2025
    },
    {
      "lat": 46.4771,
      "lng": 6.8201,
      "country": "CH",
      "year": 2025
    },
    {
      "lat": 46.1554,
      "lng": 6.0471,
      "country": "CH",
      "year": 2025
    },
    {
      "lat": 56.3496,
      "lng": 16.4115,
      "country": "SE",
      "year": 2025
    },
    {
      "lat": 51.75,
      "lng": 5.85,
      "country": "NL",
      "year": 2025
    },
    {
      "lat": 47.8043,
      "lng": 13.0054,
      "country": "AT",
      "year": 2025
    },
    {
      "lat": 47.8109,
      "lng": 12.9909,
      "country": "AT",
      "year": 2025
    },
    {
      "lat": 51.35,
      "lng": 6.2,
      "country": "NL",
      "year": 2025
    },
    {
      "lat": 45.397,
      "lng": 5.3737,
      "country": "FR",
      "year": 2025
    },
    {
      "lat": 47.7938,
      "lng": 13.0597,
      "country": "AT",
      "year": 2025
    },
    {
      "lat": 50.0395,
      "lng": 36.2097,
      "country": "UA",
      "year": 2025
    },
    {
      "lat": 46.5213,
      "lng": 6.6893,
      "country": "CH",
      "year": 2025
    },
    {
      "lat": 46.2011,
      "lng": 6.1107,
      "country": "CH",
      "year": 2025
    },
    {
      "lat": 47.5103,
      "lng": 8.2683,
      "country": "CH",
      "year": 2025
    },
    {
      "lat": 46.6548,
      "lng": 6.4915,
      "country": "CH",
      "year": 2025
    },
    {
      "lat": 46.5213,
      "lng": 6.6893,
      "country": "CH",
      "year": 2025
    },
    {
      "lat": 46.2011,
      "lng": 6.1107,
      "country": "CH",
      "year": 2025
    },
    {
      "lat": 46.2011,
      "lng": 6.1107,
      "country": "CH",
      "year": 2025
    },
    {
      "lat": 46.2004,
      "lng": 6.0459,
      "country": "CH",
      "year": 2025
    },
    {
      "lat": 46.4743,
      "lng": 6.4295,
      "country": "CH",
      "year": 2025
    },
    {
      "lat": 46.2476,
      "lng": 6.2392,
      "country": "CH",
      "year": 2025
    },
    {
      "lat": 46.2004,
      "lng": 6.0459,
      "country": "CH",
      "year": 2025
    },
    {
      "lat": 46.2011,
      "lng": 6.1107,
      "country": "CH",
      "year": 2025
    },
    {
      "lat": 46.2011,
      "lng": 6.1107,
      "country": "CH",
      "year": 2025
    },
    {
      "lat": 46.973,
      "lng": 7.0772,
      "country": "CH",
      "year": 2025
    },
    {
      "lat": 46.9728,
      "lng": 7.0115,
      "country": "CH",
      "year": 2025
    },
    {
      "lat": 46.2011,
      "lng": 6.1107,
      "country": "CH",
      "year": 2025
    },
    {
      "lat": 46.2011,
      "lng": 6.1107,
      "country": "CH",
      "year": 2025
    },
    {
      "lat": 46.2011,
      "lng": 6.1107,
      "country": "CH",
      "year": 2025
    },
    {
      "lat": 46.2004,
      "lng": 6.0459,
      "country": "CH",
      "year": 2025
    },
    {
      "lat": 46.9728,
      "lng": 7.0115,
      "country": "CH",
      "year": 2025
    },
    {
      "lat": 46.2453,
      "lng": 6.0448,
      "country": "FR",
      "year": 2025
    },
    {
      "lat": 46.2011,
      "lng": 6.1107,
      "country": "CH",
      "year": 2025
    },
    {
      "lat": 47.9412,
      "lng": 13.1757,
      "country": "AT",
      "year": 2025
    },
    {
      "lat": 47.9818,
      "lng": 12.9247,
      "country": "AT",
      "year": 2025
    },
    {
      "lat": 47.8112,
      "lng": 12.991,
      "country": "AT",
      "year": 2025
    },
    {
      "lat": 47.8109,
      "lng": 12.9909,
      "country": "AT",
      "year": 2025
    },
    {
      "lat": 47.7938,
      "lng": 13.0597,
      "country": "AT",
      "year": 2025
    },
    {
      "lat": 47.8043,
      "lng": 13.0054,
      "country": "AT",
      "year": 2025
    },
    {
      "lat": 50.1945,
      "lng": 8.7525,
      "country": "DE",
      "year": 2025
    },
    {
      "lat": 42.3606,
      "lng": 13.729,
      "country": "IT",
      "year": 2025
    },
    {
      "lat": 42.3622,
      "lng": 13.7291,
      "country": "IT",
      "year": 2025
    },
    {
      "lat": 47.8112,
      "lng": 12.991,
      "country": "AT",
      "year": 2025
    },
    {
      "lat": 42.74,
      "lng": 17.5369,
      "country": "HR",
      "year": 2025
    },
    {
      "lat": 52.15,
      "lng": 6.2,
      "country": "NL",
      "year": 2025
    },
    {
      "lat": 55.7067,
      "lng": 11.6216,
      "country": "DK",
      "year": 2025
    },
    {
      "lat": 56.3496,
      "lng": 16.4115,
      "country": "SE",
      "year": 2025
    },
    {
      "lat": 47.3014,
      "lng": 11.4655,
      "country": "AT",
      "year": 2025
    },
    {
      "lat": 52.05,
      "lng": 4.3,
      "country": "NL",
      "year": 2025
    },
    {
      "lat": 51.15,
      "lng": 5.85,
      "country": "NL",
      "year": 2025
    },
    {
      "lat": 49.9958,
      "lng": 8.9042,
      "country": "DE",
      "year": 2025
    },
    {
      "lat": 50.4162,
      "lng": 8.2274,
      "country": "DE",
      "year": 2025
    },
    {
      "lat": 49.2952,
      "lng": 8.6144,
      "country": "DE",
      "year": 2025
    },
    {
      "lat": 53.286,
      "lng": 12.3304,
      "country": "DE",
      "year": 2025
    },
    {
      "lat": 49.6101,
      "lng": 6.1233,
      "country": "LU",
      "year": 2025
    },
    {
      "lat": 52.8012,
      "lng": 21.8818,
      "country": "PL",
      "year": 2025
    },
    {
      "lat": 50.5971,
      "lng": 36.5755,
      "country": "RU",
      "year": 2025
    },
    {
      "lat": 52.3874,
      "lng": 16.9173,
      "country": "PL",
      "year": 2025
    },
    {
      "lat": 49.6104,
      "lng": 6.1398,
      "country": "LU",
      "year": 2025
    },
    {
      "lat": 49.8332,
      "lng": 34.5782,
      "country": "UA",
      "year": 2025
    },
    {
      "lat": 56.3496,
      "lng": 16.4115,
      "country": "SE",
      "year": 2025
    },
    {
      "lat": 47.7056,
      "lng": 13.0866,
      "country": "AT",
      "year": 2025
    },
    {
      "lat": 47.7867,
      "lng": 13.0689,
      "country": "AT",
      "year": 2025
    },
    {
      "lat": 51.9,
      "lng": 4.05,
      "country": "NL",
      "year": 2025
    },
    {
      "lat": 51.3131,
      "lng": 13.2986,
      "country": "DE",
      "year": 2025
    },
    {
      "lat": 47.4828,
      "lng": 13.1883,
      "country": "AT",
      "year": 2025
    },
    {
      "lat": 53.6,
      "lng": 19.56,
      "country": "PL",
      "year": 2025
    },
    {
      "lat": 51.2817,
      "lng": 6.3775,
      "country": "DE",
      "year": 2025
    },
    {
      "lat": 49.3525,
      "lng": 11.3499,
      "country": "DE",
      "year": 2025
    },
    {
      "lat": 52.0,
      "lng": 4.35,
      "country": "NL",
      "year": 2025
    },
    {
      "lat": 51.65,
      "lng": 5.25,
      "country": "NL",
      "year": 2025
    },
    {
      "lat": 51.35,
      "lng": 6.2,
      "country": "NL",
      "year": 2025
    },
    {
      "lat": 52.25,
      "lng": 6.75,
      "country": "NL",
      "year": 2025
    },
    {
      "lat": 53.6119,
      "lng": 10.882,
      "country": "DE",
      "year": 2025
    },
    {
      "lat": 49.6373,
      "lng": 5.6878,
      "country": "BE",
      "year": 2025
    },
    {
      "lat": 48.3888,
      "lng": 2.8018,
      "country": "FR",
      "year": 2025
    },
    {
      "lat": 55.7364,
      "lng": 12.0066,
      "country": "DK",
      "year": 2025
    },
    {
      "lat": 50.0395,
      "lng": 36.2098,
      "country": "UA",
      "year": 2025
    },
    {
      "lat": 55.1995,
      "lng": 11.4973,
      "country": "DK",
      "year": 2025
    },
    {
      "lat": 48.8774,
      "lng": 2.2829,
      "country": "FR",
      "year": 2025
    },
    {
      "lat": 52.4417,
      "lng": 13.3231,
      "country": "DE",
      "year": 2025
    },
    {
      "lat": 50.2354,
      "lng": 8.8404,
      "country": "DE",
      "year": 2025
    },
    {
      "lat": 52.4542,
      "lng": 13.4738,
      "country": "DE",
      "year": 2025
    },
    {
      "lat": 51.2852,
      "lng": 13.4009,
      "country": "DE",
      "year": 2025
    },
    {
      "lat": 47.7913,
      "lng": 35.1412,
      "country": "UA",
      "year": 2025
    },
    {
      "lat": 52.0377,
      "lng": 10.5538,
      "country": "DE",
      "year": 2025
    },
    {
      "lat": 55.6649,
      "lng": 11.3254,
      "country": "DK",
      "year": 2025
    },
    {
      "lat": 51.15,
      "lng": 5.9,
      "country": "NL",
      "year": 2025
    },
    {
      "lat": 51.5,
      "lng": 6.15,
      "country": "NL",
      "year": 2025
    },
    {
      "lat": 50.7674,
      "lng": 6.4862,
      "country": "DE",
      "year": 2025
    },
    {
      "lat": 50.4162,
      "lng": 8.2274,
      "country": "DE",
      "year": 2025
    },
    {
      "lat": 49.5958,
      "lng": 8.5866,
      "country": "DE",
      "year": 2025
    },
    {
      "lat": 52.4111,
      "lng": 13.0867,
      "country": "DE",
      "year": 2025
    },
    {
      "lat": 52.3046,
      "lng": 10.6116,
      "country": "DE",
      "year": 2025
    },
    {
      "lat": 55.6726,
      "lng": 11.8143,
      "country": "DK",
      "year": 2025
    },
    {
      "lat": 50.2851,
      "lng": 21.4923,
      "country": "PL",
      "year": 2025
    },
    {
      "lat": 46.1851,
      "lng": 8.8027,
      "country": "CH",
      "year": 2025
    },
    {
      "lat": 55.9881,
      "lng": 11.2966,
      "country": "DK",
      "year": 2025
    },
    {
      "lat": 46.0915,
      "lng": 8.6033,
      "country": "IT",
      "year": 2025
    },
    {
      "lat": 52.5146,
      "lng": 13.3711,
      "country": "DE",
      "year": 2025
    },
    {
      "lat": 48.982,
      "lng": 30.9768,
      "country": "UA",
      "year": 2025
    },
    {
      "lat": 50.095,
      "lng": 8.8058,
      "country": "DE",
      "year": 2025
    },
    {
      "lat": 46.9482,
      "lng": 12.5685,
      "country": "AT",
      "year": 2025
    },
    {
      "lat": 55.7365,
      "lng": 12.0063,
      "country": "DK",
      "year": 2025
    },
    {
      "lat": 49.6864,
      "lng": 9.6491,
      "country": "DE",
      "year": 2025
    },
    {
      "lat": 55.8752,
      "lng": 12.2364,
      "country": "DK",
      "year": 2025
    },
    {
      "lat": 49.0129,
      "lng": 8.419,
      "country": "DE",
      "year": 2025
    },
    {
      "lat": 49.6094,
      "lng": 6.147,
      "country": "LU",
      "year": 2025
    },
    {
      "lat": 43.4623,
      "lng": -3.7884,
      "country": "ES",
      "year": 2025
    },
    {
      "lat": 52.1972,
      "lng": 21.1693,
      "country": "PL",
      "year": 2025
    },
    {
      "lat": 52.4574,
      "lng": 13.4684,
      "country": "DE",
      "year": 2025
    },
    {
      "lat": 47.1531,
      "lng": 7.7353,
      "country": "CH",
      "year": 2025
    },
    {
      "lat": 46.2987,
      "lng": 7.6658,
      "country": "CH",
      "year": 2025
    },
    {
      "lat": 46.7923,
      "lng": 6.882,
      "country": "CH",
      "year": 2025
    },
    {
      "lat": 47.5582,
      "lng": 7.5383,
      "country": "FR",
      "year": 2025
    },
    {
      "lat": 47.1534,
      "lng": 7.2738,
      "country": "CH",
      "year": 2025
    },
    {
      "lat": 47.6029,
      "lng": 7.6713,
      "country": "DE",
      "year": 2025
    },
    {
      "lat": 46.1562,
      "lng": 6.1118,
      "country": "CH",
      "year": 2025
    },
    {
      "lat": 47.0175,
      "lng": 6.9454,
      "country": "CH",
      "year": 2025
    },
    {
      "lat": 46.7923,
      "lng": 6.882,
      "country": "CH",
      "year": 2025
    },
    {
      "lat": 50.5309,
      "lng": 36.6383,
      "country": "RU",
      "year": 2025
    },
    {
      "lat": 50.2411,
      "lng": 38.1409,
      "country": "RU",
      "year": 2025
    },
    {
      "lat": 50.4503,
      "lng": 40.1324,
      "country": "RU",
      "year": 2025
    },
    {
      "lat": 50.9727,
      "lng": 39.7663,
      "country": "RU",
      "year": 2025
    },
    {
      "lat": 49.4061,
      "lng": 43.6847,
      "country": "RU",
      "year": 2025
    },
    {
      "lat": 49.4082,
      "lng": 43.6632,
      "country": "RU",
      "year": 2025
    },
    {
      "lat": 49.1921,
      "lng": 43.9934,
      "country": "RU",
      "year": 2025
    },
    {
      "lat": 50.9673,
      "lng": 39.807,
      "country": "RU",
      "year": 2025
    },
    {
      "lat": 50.232,
      "lng": 43.5295,
      "country": "RU",
      "year": 2025
    },
    {
      "lat": 48.0421,
      "lng": 7.2654,
      "country": "FR",
      "year": 2025
    },
    {
      "lat": 51.3,
      "lng": 6.0,
      "country": "NL",
      "year": 2025
    },
    {
      "lat": 55.1772,
      "lng": 11.7831,
      "country": "DK",
      "year": 2025
    },
    {
      "lat": 48.012,
      "lng": 7.8028,
      "country": "DE",
      "year": 2025
    },
    {
      "lat": 49.9195,
      "lng": 13.542,
      "country": "CZ",
      "year": 2025
    },
    {
      "lat": 47.5517,
      "lng": 8.6675,
      "country": "CH",
      "year": 2025
    },
    {
      "lat": 46.865,
      "lng": 9.5045,
      "country": "CH",
      "year": 2025
    },
    {
      "lat": 46.2011,
      "lng": 6.1107,
      "country": "CH",
      "year": 2025
    },
    {
      "lat": 47.5581,
      "lng": 7.6047,
      "country": "CH",
      "year": 2025
    },
    {
      "lat": 47.1534,
      "lng": 7.2738,
      "country": "CH",
      "year": 2025
    },
    {
      "lat": 46.2019,
      "lng": 6.1754,
      "country": "CH",
      "year": 2025
    },
    {
      "lat": 46.1554,
      "lng": 6.0471,
      "country": "CH",
      "year": 2025
    },
    {
      "lat": 47.4231,
      "lng": 7.6706,
      "country": "CH",
      "year": 2025
    },
    {
      "lat": 46.1546,
      "lng": 5.9824,
      "country": "CH",
      "year": 2025
    },
    {
      "lat": 47.4682,
      "lng": 7.6044,
      "country": "CH",
      "year": 2025
    },
    {
      "lat": 47.4193,
      "lng": 8.3994,
      "country": "CH",
      "year": 2025
    },
    {
      "lat": 47.5131,
      "lng": 7.6046,
      "country": "CH",
      "year": 2025
    },
    {
      "lat": 47.0898,
      "lng": 9.5132,
      "country": "CH",
      "year": 2025
    },
    {
      "lat": 46.7598,
      "lng": 10.2207,
      "country": "CH",
      "year": 2025
    },
    {
      "lat": 47.1534,
      "lng": 7.2738,
      "country": "CH",
      "year": 2025
    },
    {
      "lat": 47.1534,
      "lng": 7.2738,
      "country": "CH",
      "year": 2025
    },
    {
      "lat": 47.4233,
      "lng": 7.4718,
      "country": "CH",
      "year": 2025
    },
    {
      "lat": 46.7033,
      "lng": 7.7328,
      "country": "CH",
      "year": 2025
    },
    {
      "lat": 46.1554,
      "lng": 6.0471,
      "country": "CH",
      "year": 2025
    },
    {
      "lat": 46.2011,
      "lng": 6.1107,
      "country": "CH",
      "year": 2025
    },
    {
      "lat": 46.2011,
      "lng": 6.1107,
      "country": "CH",
      "year": 2025
    },
    {
      "lat": 47.7867,
      "lng": 13.0689,
      "country": "AT",
      "year": 2025
    },
    {
      "lat": 47.3014,
      "lng": 11.4655,
      "country": "AT",
      "year": 2025
    },
    {
      "lat": 47.7056,
      "lng": 13.0866,
      "country": "AT",
      "year": 2025
    },
    {
      "lat": 47.8528,
      "lng": 7.2843,
      "country": "FR",
      "year": 2025
    },
    {
      "lat": 49.9017,
      "lng": 8.5883,
      "country": "DE",
      "year": 2025
    },
    {
      "lat": 49.9026,
      "lng": 36.0204,
      "country": "UA",
      "year": 2025
    },
    {
      "lat": 48.9022,
      "lng": 2.8692,
      "country": "FR",
      "year": 2025
    },
    {
      "lat": 45.3628,
      "lng": 5.4105,
      "country": "FR",
      "year": 2025
    },
    {
      "lat": 49.9026,
      "lng": 36.0204,
      "country": "UA",
      "year": 2025
    },
    {
      "lat": 49.0897,
      "lng": 21.2685,
      "country": "SK",
      "year": 2025
    },
    {
      "lat": 49.9006,
      "lng": 36.0216,
      "country": "UA",
      "year": 2025
    },
    {
      "lat": 46.0572,
      "lng": 3.111,
      "country": "FR",
      "year": 2025
    },
    {
      "lat": 52.0,
      "lng": 5.5,
      "country": "NL",
      "year": 2025
    },
    {
      "lat": 57.4563,
      "lng": 10.1564,
      "country": "DK",
      "year": 2025
    },
    {
      "lat": 49.5211,
      "lng": 34.504,
      "country": "UA",
      "year": 2025
    },
    {
      "lat": 49.6226,
      "lng": 34.8011,
      "country": "UA",
      "year": 2025
    },
    {
      "lat": 49.5894,
      "lng": 34.6591,
      "country": "UA",
      "year": 2025
    },
    {
      "lat": 49.5896,
      "lng": 34.6591,
      "country": "UA",
      "year": 2025
    },
    {
      "lat": 55.2201,
      "lng": 11.7814,
      "country": "DK",
      "year": 2025
    },
    {
      "lat": 55.5857,
      "lng": 11.8575,
      "country": "DK",
      "year": 2025
    },
    {
      "lat": 55.7348,
      "lng": 10.892,
      "country": "DK",
      "year": 2025
    },
    {
      "lat": 55.7936,
      "lng": 12.5029,
      "country": "DK",
      "year": 2025
    },
    {
      "lat": 57.4579,
      "lng": 10.1621,
      "country": "DK",
      "year": 2025
    },
    {
      "lat": 55.6444,
      "lng": 12.0701,
      "country": "DK",
      "year": 2025
    },
    {
      "lat": 55.9026,
      "lng": 11.943,
      "country": "DK",
      "year": 2025
    },
    {
      "lat": 55.2934,
      "lng": 11.7139,
      "country": "DK",
      "year": 2025
    },
    {
      "lat": 55.953,
      "lng": 11.8543,
      "country": "DK",
      "year": 2025
    },
    {
      "lat": 55.9893,
      "lng": 12.2474,
      "country": "DK",
      "year": 2025
    },
    {
      "lat": 55.633,
      "lng": 12.534,
      "country": "DK",
      "year": 2025
    },
    {
      "lat": 57.0739,
      "lng": 9.9104,
      "country": "DK",
      "year": 2025
    },
    {
      "lat": 56.1009,
      "lng": 12.1717,
      "country": "DK",
      "year": 2025
    },
    {
      "lat": 55.7405,
      "lng": 10.9384,
      "country": "DK",
      "year": 2025
    },
    {
      "lat": 55.6345,
      "lng": 12.5312,
      "country": "DK",
      "year": 2025
    },
    {
      "lat": 55.8378,
      "lng": 11.372,
      "country": "DK",
      "year": 2025
    },
    {
      "lat": 51.95,
      "lng": 5.9,
      "country": "NL",
      "year": 2025
    },
    {
      "lat": 51.95,
      "lng": 5.65,
      "country": "NL",
      "year": 2025
    },
    {
      "lat": 51.8,
      "lng": 5.85,
      "country": "NL",
      "year": 2025
    },
    {
      "lat": 47.7991,
      "lng": 13.0341,
      "country": "AT",
      "year": 2025
    },
    {
      "lat": 47.7991,
      "lng": 13.0341,
      "country": "AT",
      "year": 2025
    },
    {
      "lat": 49.1503,
      "lng": 5.3825,
      "country": "FR",
      "year": 2025
    },
    {
      "lat": 45.7749,
      "lng": 4.8565,
      "country": "FR",
      "year": 2025
    },
    {
      "lat": 50.9799,
      "lng": 0.1085,
      "country": "GB",
      "year": 2025
    },
    {
      "lat": 50.872,
      "lng": -0.1019,
      "country": "GB",
      "year": 2025
    },
    {
      "lat": 52.0552,
      "lng": 26.4437,
      "country": "BY",
      "year": 2025
    },
    {
      "lat": 50.4846,
      "lng": 40.2158,
      "country": "RU",
      "year": 2025
    },
    {
      "lat": 50.4968,
      "lng": 40.2191,
      "country": "RU",
      "year": 2025
    },
    {
      "lat": 49.5461,
      "lng": 43.7469,
      "country": "RU",
      "year": 2025
    },
    {
      "lat": 48.0051,
      "lng": 7.8487,
      "country": "DE",
      "year": 2025
    },
    {
      "lat": 52.1662,
      "lng": 11.6437,
      "country": "DE",
      "year": 2025
    },
    {
      "lat": 46.07,
      "lng": 11.1174,
      "country": "IT",
      "year": 2025
    },
    {
      "lat": 44.6873,
      "lng": 33.6929,
      "country": "UA",
      "year": 2025
    },
    {
      "lat": 49.0896,
      "lng": 21.2685,
      "country": "SK",
      "year": 2025
    },
    {
      "lat": 47.5322,
      "lng": 7.6216,
      "country": "CH",
      "year": 2025
    },
    {
      "lat": 47.7991,
      "lng": 13.0341,
      "country": "AT",
      "year": 2025
    },
    {
      "lat": 47.7991,
      "lng": 13.0341,
      "country": "AT",
      "year": 2025
    },
    {
      "lat": 49.176,
      "lng": 16.6314,
      "country": "CZ",
      "year": 2025
    },
    {
      "lat": 49.7052,
      "lng": 18.15,
      "country": "CZ",
      "year": 2025
    },
    {
      "lat": 50.8,
      "lng": 5.65,
      "country": "NL",
      "year": 2025
    },
    {
      "lat": 52.15,
      "lng": 4.5,
      "country": "NL",
      "year": 2025
    },
    {
      "lat": 51.2,
      "lng": 5.6,
      "country": "NL",
      "year": 2025
    },
    {
      "lat": 51.25,
      "lng": 6.0,
      "country": "NL",
      "year": 2025
    },
    {
      "lat": 51.2,
      "lng": 5.6,
      "country": "NL",
      "year": 2025
    },
    {
      "lat": 51.7,
      "lng": 5.7,
      "country": "NL",
      "year": 2025
    },
    {
      "lat": 51.35,
      "lng": 6.2,
      "country": "NL",
      "year": 2025
    },
    {
      "lat": 52.0,
      "lng": 4.3,
      "country": "NL",
      "year": 2025
    },
    {
      "lat": 51.5,
      "lng": 6.05,
      "country": "NL",
      "year": 2025
    },
    {
      "lat": 56.0988,
      "lng": 14.2856,
      "country": "SE",
      "year": 2025
    },
    {
      "lat": 56.0998,
      "lng": 14.2847,
      "country": "SE",
      "year": 2025
    },
    {
      "lat": 56.099,
      "lng": 14.2819,
      "country": "SE",
      "year": 2025
    },
    {
      "lat": 56.0952,
      "lng": 14.2972,
      "country": "SE",
      "year": 2025
    },
    {
      "lat": 56.0414,
      "lng": 14.1579,
      "country": "SE",
      "year": 2025
    },
    {
      "lat": 56.0945,
      "lng": 14.2993,
      "country": "SE",
      "year": 2025
    },
    {
      "lat": 56.1012,
      "lng": 14.2857,
      "country": "SE",
      "year": 2025
    },
    {
      "lat": 56.093,
      "lng": 14.2977,
      "country": "SE",
      "year": 2025
    },
    {
      "lat": 56.101,
      "lng": 14.2829,
      "country": "SE",
      "year": 2025
    },
    {
      "lat": 56.0996,
      "lng": 14.2817,
      "country": "SE",
      "year": 2025
    },
    {
      "lat": 56.0996,
      "lng": 14.2861,
      "country": "SE",
      "year": 2025
    },
    {
      "lat": 50.4162,
      "lng": 8.2274,
      "country": "DE",
      "year": 2025
    },
    {
      "lat": 49.3232,
      "lng": 9.1399,
      "country": "DE",
      "year": 2025
    },
    {
      "lat": 51.3072,
      "lng": 12.4387,
      "country": "DE",
      "year": 2025
    },
    {
      "lat": 48.0291,
      "lng": 7.7775,
      "country": "DE",
      "year": 2025
    },
    {
      "lat": 50.2308,
      "lng": 13.8458,
      "country": "CZ",
      "year": 2025
    },
    {
      "lat": 52.296,
      "lng": 20.8855,
      "country": "PL",
      "year": 2025
    },
    {
      "lat": 48.3079,
      "lng": 19.5174,
      "country": "SK",
      "year": 2025
    },
    {
      "lat": 48.9849,
      "lng": 21.2635,
      "country": "SK",
      "year": 2025
    },
    {
      "lat": 50.0713,
      "lng": 36.2145,
      "country": "UA",
      "year": 2025
    },
    {
      "lat": 48.2701,
      "lng": 19.6351,
      "country": "SK",
      "year": 2025
    },
    {
      "lat": 55.9249,
      "lng": 43.529,
      "country": "RU",
      "year": 2025
    },
    {
      "lat": 55.9813,
      "lng": 12.4052,
      "country": "DK",
      "year": 2025
    },
    {
      "lat": 52.585,
      "lng": 13.1347,
      "country": "DE",
      "year": 2025
    },
    {
      "lat": 49.8917,
      "lng": 36.1709,
      "country": "UA",
      "year": 2025
    },
    {
      "lat": 49.6148,
      "lng": 6.1652,
      "country": "LU",
      "year": 2025
    },
    {
      "lat": 51.4788,
      "lng": 6.7778,
      "country": "DE",
      "year": 2025
    },
    {
      "lat": 50.9572,
      "lng": 13.9485,
      "country": "DE",
      "year": 2025
    },
    {
      "lat": 49.7539,
      "lng": 8.5789,
      "country": "DE",
      "year": 2025
    },
    {
      "lat": 50.5601,
      "lng": 42.6927,
      "country": "RU",
      "year": 2025
    },
    {
      "lat": 48.2701,
      "lng": 19.635,
      "country": "SK",
      "year": 2025
    },
    {
      "lat": 49.8984,
      "lng": 36.1861,
      "country": "UA",
      "year": 2025
    },
    {
      "lat": 51.4386,
      "lng": 0.452,
      "country": "GB",
      "year": 2025
    },
    {
      "lat": 47.0619,
      "lng": 15.4337,
      "country": "AT",
      "year": 2025
    },
    {
      "lat": 47.4553,
      "lng": 11.0442,
      "country": "DE",
      "year": 2025
    },
    {
      "lat": 48.2115,
      "lng": 19.9458,
      "country": "SK",
      "year": 2025
    },
    {
      "lat": 51.35,
      "lng": 6.05,
      "country": "NL",
      "year": 2025
    },
    {
      "lat": 50.85,
      "lng": 5.65,
      "country": "NL",
      "year": 2025
    },
    {
      "lat": 51.15,
      "lng": 6.1,
      "country": "NL",
      "year": 2025
    },
    {
      "lat": 51.35,
      "lng": 6.2,
      "country": "NL",
      "year": 2025
    },
    {
      "lat": 50.85,
      "lng": 5.65,
      "country": "NL",
      "year": 2025
    },
    {
      "lat": 51.35,
      "lng": 6.2,
      "country": "NL",
      "year": 2025
    },
    {
      "lat": 47.2653,
      "lng": 11.3674,
      "country": "AT",
      "year": 2025
    },
    {
      "lat": 51.55,
      "lng": 6.05,
      "country": "NL",
      "year": 2025
    },
    {
      "lat": 52.05,
      "lng": 5.3,
      "country": "NL",
      "year": 2025
    },
    {
      "lat": 50.85,
      "lng": 5.95,
      "country": "NL",
      "year": 2025
    },
    {
      "lat": 51.5173,
      "lng": 7.4522,
      "country": "DE",
      "year": 2025
    },
    {
      "lat": 48.2846,
      "lng": 11.6508,
      "country": "DE",
      "year": 2025
    },
    {
      "lat": 49.3348,
      "lng": 8.6576,
      "country": "DE",
      "year": 2025
    },
    {
      "lat": 48.9722,
      "lng": 8.396,
      "country": "DE",
      "year": 2025
    },
    {
      "lat": 49.3508,
      "lng": 8.6387,
      "country": "DE",
      "year": 2025
    },
    {
      "lat": 53.6156,
      "lng": 10.0333,
      "country": "DE",
      "year": 2025
    },
    {
      "lat": 50.8263,
      "lng": 6.4509,
      "country": "DE",
      "year": 2025
    },
    {
      "lat": 59.9026,
      "lng": 10.7663,
      "country": "NO",
      "year": 2025
    },
    {
      "lat": 56.8927,
      "lng": 14.7771,
      "country": "SE",
      "year": 2025
    },
    {
      "lat": 50.4386,
      "lng": 40.0983,
      "country": "RU",
      "year": 2025
    },
    {
      "lat": 53.589,
      "lng": 34.3267,
      "country": "RU",
      "year": 2025
    },
    {
      "lat": 49.7601,
      "lng": 8.3952,
      "country": "DE",
      "year": 2025
    },
    {
      "lat": 50.646,
      "lng": 36.4693,
      "country": "RU",
      "year": 2025
    },
    {
      "lat": 49.5228,
      "lng": 10.9996,
      "country": "DE",
      "year": 2025
    },
    {
      "lat": 47.5576,
      "lng": 41.9803,
      "country": "RU",
      "year": 2025
    },
    {
      "lat": 56.4235,
      "lng": 12.8431,
      "country": "SE",
      "year": 2025
    },
    {
      "lat": 50.5218,
      "lng": 18.7785,
      "country": "PL",
      "year": 2025
    },
    {
      "lat": 49.1777,
      "lng": 16.5683,
      "country": "CZ",
      "year": 2025
    },
    {
      "lat": 50.0942,
      "lng": 14.4968,
      "country": "CZ",
      "year": 2025
    }
  ],
  "source": "GBIF.org occurrence search API",
  "source_url": "https://www.gbif.org/species/3171939",
  "accessed": "2026-05-16",
  "bulgaria_points": [
    {
      "lat": 42.1632,
      "lng": 27.8597,
      "year": 2024
    },
    {
      "lat": 43.6654,
      "lng": 28.5279,
      "year": 2024
    },
    {
      "lat": 42.1442,
      "lng": 23.3612,
      "year": 2023
    },
    {
      "lat": 42.1442,
      "lng": 23.3612,
      "year": 2023
    },
    {
      "lat": 41.4437,
      "lng": 23.0034,
      "year": 2023
    },
    {
      "lat": 42.5887,
      "lng": 23.2796,
      "year": 2023
    },
    {
      "lat": 41.5257,
      "lng": 23.4,
      "year": 2023
    },
    {
      "lat": 41.7257,
      "lng": 23.5185,
      "year": 2023
    },
    {
      "lat": 41.748,
      "lng": 23.5362,
      "year": 2023
    },
    {
      "lat": 42.2201,
      "lng": 23.321,
      "year": 2023
    },
    {
      "lat": 41.8501,
      "lng": 24.1148,
      "year": 2023
    },
    {
      "lat": 42.5815,
      "lng": 23.2919,
      "year": 2023
    },
    {
      "lat": 41.4168,
      "lng": 23.0166,
      "year": 2023
    },
    {
      "lat": 41.4542,
      "lng": 23.0059,
      "year": 2023
    },
    {
      "lat": 41.4425,
      "lng": 23.0036,
      "year": 2023
    },
    {
      "lat": 42.2551,
      "lng": 22.5529,
      "year": 2022
    },
    {
      "lat": 41.7566,
      "lng": 23.4162,
      "year": 2022
    },
    {
      "lat": 42.497,
      "lng": 27.4716,
      "year": 2022
    },
    {
      "lat": 41.4546,
      "lng": 23.0082,
      "year": 2021
    },
    {
      "lat": 41.4373,
      "lng": 23.0003,
      "year": 2021
    },
    {
      "lat": 41.4527,
      "lng": 22.9995,
      "year": 2021
    },
    {
      "lat": 41.4804,
      "lng": 24.6242,
      "year": 2021
    },
    {
      "lat": 42.261,
      "lng": 23.8307,
      "year": 2021
    },
    {
      "lat": 42.261,
      "lng": 23.8307,
      "year": 2021
    },
    {
      "lat": 43.3944,
      "lng": 22.6776,
      "year": 2020
    },
    {
      "lat": 41.7844,
      "lng": 23.4564,
      "year": 2016
    },
    {
      "lat": 42.3789,
      "lng": 27.7176,
      "year": 2016
    },
    {
      "lat": 41.4597,
      "lng": 23.2619,
      "year": 2015
    },
    {
      "lat": 41.8706,
      "lng": 26.2342,
      "year": 2012
    },
    {
      "lat": 43.5883,
      "lng": 24.9246,
      "year": 2011
    },
    {
      "lat": 43.7021,
      "lng": 26.2614,
      "year": 1932
    },
    {
      "lat": 43.8091,
      "lng": 25.9425,
      "year": 1932
    },
    {
      "lat": 43.6475,
      "lng": 26.3679,
      "year": 1932
    },
    {
      "lat": 42.4908,
      "lng": 26.011,
      "year": 1931
    },
    {
      "lat": 42.6542,
      "lng": 23.2282,
      "year": 1930
    },
    {
      "lat": 43.2142,
      "lng": 27.9147,
      "year": 1893
    }
  ],
  "bulgaria_total_count": 36,
  "bulgaria_accessed": "2026-05-16"
}